{
  "coins": [
    {
      "item": {
        "id": "axie-infinity",
        "coin_id": 13029,
        "name": "Axie Infinity",
        "symbol": "AXS",
        "market_cap_rank": 210,
        "thumb": "https://coin-images.coingecko.com/coins/images/13029/standard/axie_infinity_logo.png?1696512817",
        "small": "https://coin-images.coingecko.com/coins/images/13029/small/axie_infinity_logo.png?1696512817",
        "large": "https://coin-images.coingecko.com/coins/images/13029/large/axie_infinity_logo.png?1696512817",
        "slug": "axie-infinity",
        "price_btc": 0.000021181251312087307,
        "score": 0,
        "data": {
          "price": 2.0198998614775157,
          "price_btc": "0.0000211812513120873",
          "price_change_percentage_24h": {
            "aed": 63.18187102278293,
            "ars": 62.103329602962944,
            "aud": 62.63398389577747,
            "bch": 63.83188876776864,
            "bdt": 63.39402956379203,
            "bhd": 63.39378451842681,
            "bmd": 63.18169328914832,
            "bnb": 61.91772562127484,
            "brl": 62.83002533728595,
            "btc": 63.26413733474215,
            "cad": 63.36845657675371,
            "chf": 63.41739438982893,
            "clp": 63.37338705188894,
            "cny": 63.17115682752662,
            "czk": 63.21291389468481,
            "dkk": 63.43450092028067,
            "dot": 56.75402417510013,
            "eos": 78.34799244706547,
            "eth": 63.26402495765174,
            "eur": 63.32120564906973,
            "gbp": 63.434300930776836,
            "gel": 62.90261929123747,
            "hkd": 63.13089631116944,
            "huf": 63.462520727498806,
            "idr": 63.115292464719474,
            "ils": 63.03727140734695,
            "inr": 63.13161515229142,
            "jpy": 63.295229353721595,
            "krw": 63.24635736592734,
            "kwd": 63.144612560272364,
            "lkr": 63.394052207707944,
            "ltc": 59.220961989041065,
            "mmk": 63.195536651397724,
            "mxn": 62.47866916601976,
            "myr": 63.18185415834685,
            "ngn": 63.05187710142582,
            "nok": 63.2983534106077,
            "nzd": 63.319317230200724,
            "php": 63.17997171424212,
            "pkr": 63.3940112635961,
            "pln": 63.30364978254719,
            "rub": 63.26102688272547,
            "sar": 63.16293835822193,
            "sek": 63.10155656762011,
            "sgd": 63.27216043231161,
            "sol": 62.26816815267896,
            "thb": 62.92857341890114,
            "try": 63.17386215101968,
            "twd": 63.309446640707925,
            "uah": 63.394003501628106,
            "usd": 63.18169328914832,
            "vef": 63.1816932891483,
            "vnd": 63.18601760371699,
            "xag": 61.4130217733988,
            "xau": 63.775190539267776,
            "xdr": 63.64006229297205,
            "xlm": 60.76424262731393,
            "xrp": 63.044488637647575,
            "yfi": 52.3476369431592,
            "zar": 63.11995348097202,
            "bits": 63.26413733474215,
            "link": 62.67865667125411,
            "sats": 63.264137334742145
          },
          "market_cap": "$339,545,972",
          "market_cap_btc": "3560.994601303372",
          "total_volume": "$743,424,386",
          "total_volume_btc": "7795.762079674898",
          "sparkline": "https://www.coingecko.com/coins/13029/sparkline.svg",
          "content": {
            "title": "What is Axie Infinity?",
            "description": "Axie Infinity is a digital game that fuses NFT collectibles and blockchain. The game allows users to discover, collect, combine, and battle fantasy creatures called Axies. Players can earn Smooth Love Potion (SLP) tokens by winning challenges against their opponents in Ranked PvP mode. With its ever-expanding world of characters and unique storytelling and art direction, Axie Infinity has become a hit for gamers around the world."
          }
        }
      }
    },
    {
      "item": {
        "id": "ronin",
        "coin_id": 20009,
        "name": "Ronin",
        "symbol": "RON",
        "market_cap_rank": 373,
        "thumb": "https://coin-images.coingecko.com/coins/images/20009/standard/photo_2024-04-06_22-52-24.jpg?1712415367",
        "small": "https://coin-images.coingecko.com/coins/images/20009/small/photo_2024-04-06_22-52-24.jpg?1712415367",
        "large": "https://coin-images.coingecko.com/coins/images/20009/large/photo_2024-04-06_22-52-24.jpg?1712415367",
        "slug": "ronin",
        "price_btc": 0.000001952928759938549,
        "score": 1,
        "data": {
          "price": 0.1862364254856008,
          "price_btc": "0.000001952928759938549",
          "price_change_percentage_24h": {
            "aed": 26.34420686096051,
            "ars": 25.50914191532801,
            "aud": 25.920003093244375,
            "bch": 26.847485662220848,
            "bdt": 26.50847144761201,
            "bhd": 26.508281720272077,
            "bmd": 26.344069249993346,
            "bnb": 25.36543730090215,
            "brl": 26.07178895207799,
            "btc": 26.407901877267893,
            "cad": 26.48867146159534,
            "chf": 26.52656175626929,
            "clp": 26.492488901403483,
            "cny": 26.335911353050673,
            "czk": 26.36824192689367,
            "dkk": 26.53980655490115,
            "dot": 21.36742110219919,
            "eos": 38.08663615471745,
            "eth": 26.407814868862655,
            "eur": 26.452087244584842,
            "gbp": 26.539651712239515,
            "gel": 26.127995107071904,
            "hkd": 26.304739489564376,
            "huf": 26.561501001086786,
            "idr": 26.29265814994411,
            "ils": 26.232250038734183,
            "inr": 26.305296055136562,
            "jpy": 26.43197499551958,
            "krw": 26.3941356663289,
            "kwd": 26.31535934949828,
            "lkr": 26.508488979753142,
            "ltc": 23.27745742868651,
            "mmk": 26.354787527781937,
            "mxn": 25.79975005151817,
            "myr": 26.34419380360441,
            "ngn": 26.24355855494671,
            "nok": 26.434393808877875,
            "nzd": 26.450625128831863,
            "php": 26.342736313836202,
            "pkr": 26.50845727861318,
            "pln": 26.438494545728986,
            "rub": 26.405493597533354,
            "sar": 26.329548170796386,
            "sek": 26.28202307747148,
            "sgd": 26.414113792186043,
            "sol": 25.636768812197403,
            "thb": 26.148090192720076,
            "try": 26.338005960428855,
            "twd": 26.44298278600968,
            "uah": 26.50845126887883,
            "usd": 26.344069249993346,
            "vef": 26.34406924999334,
            "vnd": 26.34741736759348,
            "xag": 24.974668357269493,
            "xau": 26.80358683531403,
            "xdr": 26.69896325797827,
            "xlm": 24.472348546090323,
            "xrp": 26.23783800774294,
            "yfi": 17.955758419007463,
            "zar": 26.296266960150188,
            "bits": 26.407901877267896,
            "link": 25.95459116574591,
            "sats": 26.407901877267893
          },
          "market_cap": "$135,599,502",
          "market_cap_btc": "1422.076808755428",
          "total_volume": "$24,109,943",
          "total_volume_btc": "252.8238028962344",
          "sparkline": "https://www.coingecko.com/coins/20009/sparkline.svg",
          "content": {
            "title": "What is Ronin?",
            "description": "Ronin is an EVM blockchain specifically forged for gaming. Launched by Sky Mavis, the creator of Web3’s breakout title Axie Infinity which has generated over $1.3B in revenue, Ronin is the only blockchain proven to scale a single game to accommodate millions of daily active users and has processed over $4B in NFT volumes. Ronin optimizes for near-instant transactions and negligible fees that enable millions of in-game transactions to occur seamlessly, making it the leading choice for Web3 games."
          }
        }
      }
    },
    {
      "item": {
        "id": "mind-network",
        "coin_id": 55161,
        "name": "Mind Network",
        "symbol": "FHE",
        "market_cap_rank": 864,
        "thumb": "https://coin-images.coingecko.com/coins/images/55161/standard/mind.jpg?1744276359",
        "small": "https://coin-images.coingecko.com/coins/images/55161/small/mind.jpg?1744276359",
        "large": "https://coin-images.coingecko.com/coins/images/55161/large/mind.jpg?1744276359",
        "slug": "mind-network",
        "price_btc": 0.0000014688054706807415,
        "score": 2,
        "data": {
          "price": 0.1400691546996748,
          "price_btc": "0.000001468805470680741",
          "price_change_percentage_24h": {
            "aed": 36.149557479286024,
            "ars": 35.24968461895421,
            "aud": 35.69243200681259,
            "bch": 36.70633963898125,
            "bdt": 36.32657035021818,
            "bhd": 36.326365898474776,
            "bmd": 36.14940918857486,
            "bnb": 35.09843524908373,
            "brl": 35.85599769791346,
            "btc": 36.217992510020345,
            "cad": 36.30523372227751,
            "chf": 36.34606461576118,
            "clp": 36.30934742684295,
            "cny": 36.14061817166716,
            "czk": 36.1754578642113,
            "dkk": 36.36033731980859,
            "dot": 30.796342985607904,
            "eos": 48.80307393852734,
            "eth": 36.223580657648235,
            "eur": 36.265810268836645,
            "gbp": 36.36017046008161,
            "gel": 35.9165659132687,
            "hkd": 36.107027114942774,
            "huf": 36.38371543362412,
            "idr": 36.09400816390477,
            "ils": 36.02891188593741,
            "inr": 36.10762687458545,
            "jpy": 36.24413714366389,
            "krw": 36.20336117100461,
            "kwd": 36.118471163438656,
            "lkr": 36.32658924299788,
            "ltc": 32.85530334524719,
            "mmk": 36.16095929296129,
            "mxn": 35.56284633902985,
            "myr": 36.149543408571574,
            "ngn": 36.04109803610866,
            "nok": 36.246743676852425,
            "nzd": 36.26423468086396,
            "php": 36.147972805598144,
            "pkr": 36.32655508158847,
            "pln": 36.25116266464365,
            "rub": 36.215600571178044,
            "sar": 36.133761154083174,
            "sek": 36.08254772225191,
            "sgd": 36.22488976390403,
            "sol": 35.41038204162268,
            "thb": 35.938220543001826,
            "try": 36.14287533782237,
            "twd": 36.255999229320956,
            "uah": 36.32654860544929,
            "usd": 36.14940918857486,
            "vef": 36.14940918857486,
            "vnd": 36.15301714766514,
            "xag": 34.67373151257922,
            "xau": 36.6445891216304,
            "xdr": 36.53184589334892,
            "xlm": 34.12278987308427,
            "xrp": 36.0457989119737,
            "yfi": 27.131115684167657,
            "zar": 36.09789704749342,
            "bits": 36.217992510020316,
            "link": 35.742422043697445,
            "sats": 36.21799251002033
          },
          "market_cap": "$34,769,994",
          "market_cap_btc": "364.6463419111301",
          "total_volume": "$31,072,435",
          "total_volume_btc": "325.8344920591988",
          "sparkline": "https://www.coingecko.com/coins/55161/sparkline.svg",
          "content": null
        }
      }
    },
    {
      "item": {
        "id": "dash",
        "coin_id": 19,
        "name": "Dash",
        "symbol": "DASH",
        "market_cap_rank": 105,
        "thumb": "https://coin-images.coingecko.com/coins/images/19/standard/dash-logo.png?1696501423",
        "small": "https://coin-images.coingecko.com/coins/images/19/small/dash-logo.png?1696501423",
        "large": "https://coin-images.coingecko.com/coins/images/19/large/dash-logo.png?1696501423",
        "slug": "dash",
        "price_btc": 0.0007918316664406358,
        "score": 3,
        "data": {
          "price": 75.51115133808096,
          "price_btc": "0.0007918316664406358",
          "price_change_percentage_24h": {
            "aed": -13.767398361450411,
            "ars": -14.337347903167737,
            "aud": -14.056926432613151,
            "bch": -13.40542464820777,
            "bdt": -13.655284296104925,
            "bhd": -13.655413789039574,
            "bmd": -13.767492283855006,
            "bnb": -14.427717259434566,
            "brl": -13.953329363745807,
            "btc": -13.714796433553689,
            "cad": -13.668798206627878,
            "chf": -13.64293727665131,
            "clp": -13.666192722969964,
            "cny": -13.77306022159227,
            "czk": -13.750993919035043,
            "dkk": -13.63389742058996,
            "dot": -17.133611064149406,
            "eos": -5.742969122421126,
            "eth": -13.71150450824565,
            "eur": -13.693767710890187,
            "gbp": -13.634003103991606,
            "gel": -13.914967470520564,
            "hkd": -13.794335679748434,
            "huf": -13.619090500809683,
            "idr": -13.802581450350951,
            "ils": -13.843811267840229,
            "inr": -13.793955811937577,
            "jpy": -13.70749474756873,
            "krw": -13.73332089252181,
            "kwd": -13.787087400037871,
            "lkr": -13.655272330046609,
            "ltc": -15.858258329628791,
            "mmk": -13.760176831870597,
            "mxn": -14.139001684820071,
            "myr": -13.767407273372983,
            "ngn": -13.836092965609344,
            "nok": -13.705843856135317,
            "nzd": -13.6947656359111,
            "php": -13.76840204106117,
            "pkr": -13.655293966747198,
            "pln": -13.703045016235233,
            "rub": -13.725568863510501,
            "sar": -13.77740322847894,
            "sek": -13.80984011294196,
            "sgd": -13.719685397778274,
            "sol": -14.241494844328315,
            "thb": -13.901252148238338,
            "try": -13.771630607618492,
            "twd": -13.699981697023379,
            "uah": -13.655298068518379,
            "usd": -13.767492283855006,
            "vef": -13.767492283855018,
            "vnd": -13.765207122560904,
            "xag": -14.702137445668226,
            "xau": -13.453861782976755,
            "xdr": -13.525269594150283,
            "xlm": -15.035022940632645,
            "xrp": -13.81408474567856,
            "yfi": -19.472275167174505,
            "zar": -13.800118360822603,
            "bits": -13.71479643355368,
            "link": -14.031254144767491,
            "sats": -13.714796433553689
          },
          "market_cap": "$946,115,120",
          "market_cap_btc": "9922.22208780359",
          "total_volume": "$626,244,230",
          "total_volume_btc": "6566.977236399967",
          "sparkline": "https://www.coingecko.com/coins/19/sparkline.svg",
          "content": {
            "title": "What is Dash about?",
            "description": "Dash (DASH) is digital cash designed to offer financial freedom to everyone. Payments are instant, easy and secure, with near-zero fees."
          }
        }
      }
    },
    {
      "item": {
        "id": "berachain-bera",
        "coin_id": 25235,
        "name": "Berachain",
        "symbol": "BERA",
        "market_cap_rank": 383,
        "thumb": "https://coin-images.coingecko.com/coins/images/25235/standard/BERA.png?1738822008",
        "small": "https://coin-images.coingecko.com/coins/images/25235/small/BERA.png?1738822008",
        "large": "https://coin-images.coingecko.com/coins/images/25235/large/BERA.png?1738822008",
        "slug": "berachain",
        "price_btc": 0.000009524955325340056,
        "score": 4,
        "data": {
          "price": 0.9083248037973423,
          "price_btc": "0.000009524955325340056",
          "price_change_percentage_24h": {
            "aed": 32.211343003858694,
            "ars": 31.340420227986787,
            "aud": 31.795661177626894,
            "bch": 32.73329380431511,
            "bdt": 32.383235662404246,
            "bhd": 32.383037124560374,
            "bmd": 32.21119900255277,
            "bnb": 30.992390219809035,
            "brl": 31.894408972204563,
            "btc": 32.26618240197413,
            "cad": 32.36089753954565,
            "chf": 32.39572553471034,
            "clp": 32.34260213726227,
            "cny": 32.20266227152509,
            "czk": 32.2537277936132,
            "dkk": 32.41077603060105,
            "dot": 26.94134506107675,
            "eos": 44.32149243428843,
            "eth": 32.224324724932536,
            "eur": 32.3193145608032,
            "gbp": 32.43006325562354,
            "gel": 31.985090870381043,
            "hkd": 32.16875502317796,
            "huf": 32.38963513070978,
            "idr": 32.1494404533776,
            "ils": 32.077823709366584,
            "inr": 32.1835162334144,
            "jpy": 32.32422460606369,
            "krw": 32.26449361456894,
            "kwd": 32.16485247333944,
            "lkr": 32.383254008697975,
            "ltc": 28.9230654034035,
            "mmk": 32.222415012659845,
            "mxn": 31.6589990606628,
            "myr": 32.211329340148794,
            "ngn": 32.10602082059629,
            "nok": 32.284304423144235,
            "nzd": 32.33954017474957,
            "php": 32.20314852004285,
            "pkr": 32.38322083542952,
            "pln": 32.298545897883216,
            "rub": 32.251569404933825,
            "sar": 32.19734319130472,
            "sek": 32.13406984376203,
            "sgd": 32.28346911987385,
            "sol": 31.44031366250266,
            "thb": 32.006819879926695,
            "try": 32.20554145209032,
            "twd": 32.315966276323,
            "uah": 32.383214546616884,
            "usd": 32.21119900255277,
            "vef": 32.211199002552746,
            "vnd": 32.214702599080425,
            "xag": 31.3719242609789,
            "xau": 32.802107462362414,
            "xdr": 32.58257347697837,
            "xlm": 30.158976691754596,
            "xrp": 32.03009904004199,
            "yfi": 24.09760468525531,
            "zar": 32.173417124012346,
            "bits": 32.266182401974135,
            "link": 31.720009253816762,
            "sats": 32.26618240197413
          },
          "market_cap": "$129,933,468",
          "market_cap_btc": "1362.912130074757",
          "total_volume": "$272,366,721",
          "total_volume_btc": "2856.115833231906",
          "sparkline": "https://www.coingecko.com/coins/25235/sparkline.svg",
          "content": null
        }
      }
    },
    {
      "item": {
        "id": "lighter",
        "coin_id": 71121,
        "name": "Lighter",
        "symbol": "LIT",
        "market_cap_rank": 162,
        "thumb": "https://coin-images.coingecko.com/coins/images/71121/standard/lighter.png?1765888098",
        "small": "https://coin-images.coingecko.com/coins/images/71121/small/lighter.png?1765888098",
        "large": "https://coin-images.coingecko.com/coins/images/71121/large/lighter.png?1765888098",
        "slug": "lighter",
        "price_btc": 0.000020182594200977614,
        "score": 5,
        "data": {
          "price": 1.9246652914951996,
          "price_btc": "0.00002018259420097761",
          "price_change_percentage_24h": {
            "aed": 1.0045342582144643,
            "ars": 0.33918174493393133,
            "aud": 0.6869688488916073,
            "bch": 1.4083541280198606,
            "bdt": 1.1358538373393503,
            "bhd": 1.1357021618325749,
            "bmd": 1.004424246588335,
            "bnb": 0.11118644287391115,
            "brl": 0.7624084804219453,
            "btc": 1.0510580480940823,
            "cad": 1.118788344740372,
            "chf": 1.1453956338792954,
            "clp": 1.1048113398577502,
            "cny": 0.9979025025235014,
            "czk": 1.0369146565337268,
            "dkk": 1.1568936513205925,
            "dot": -3.0124151646987984,
            "eos": 10.261287085784838,
            "eth": 1.025749911276927,
            "eur": 1.087020500124848,
            "gbp": 1.1716283717785576,
            "gel": 0.8316860679788365,
            "hkd": 0.9719986296070969,
            "huf": 1.1407427924093982,
            "idr": 0.9572430187589435,
            "ils": 0.9025304978089032,
            "inr": 0.9832756435995818,
            "jpy": 1.09077159154748,
            "krw": 1.045139342153211,
            "kwd": 0.9690172271048356,
            "lkr": 1.135867853223362,
            "ltc": -1.5008203400062747,
            "mmk": 1.0129928599263678,
            "mxn": 0.5825640893521942,
            "myr": 1.0045238196497874,
            "ngn": 0.9240720389692709,
            "nok": 1.0602740609146022,
            "nzd": 1.102472114716474,
            "php": 0.9982739782528371,
            "pkr": 1.135842510083697,
            "pln": 1.0711540163744335,
            "rub": 1.0352657280956787,
            "sar": 0.9938389236494363,
            "sek": 0.945500446372778,
            "sgd": 1.059635920374821,
            "sol": 0.4379980062722413,
            "thb": 0.8482862207281046,
            "try": 1.000102089075064,
            "twd": 1.0844625356809294,
            "uah": 1.135837705665447,
            "usd": 1.004424246588335,
            "vef": 1.0044242465883146,
            "vnd": 1.007100863643007,
            "xag": 0.363249650964667,
            "xau": 1.4558562675955575,
            "xdr": 1.2881404919005939,
            "xlm": -0.5388675106416644,
            "xrp": 0.909119407992293,
            "yfi": -5.226274657790153,
            "zar": 0.9755603007371667,
            "bits": 1.051058048094092,
            "link": 0.6643925380531374,
            "sats": 1.0510580480940814
          },
          "market_cap": "$477,970,635",
          "market_cap_btc": "5013.581089832815",
          "total_volume": "$75,732,677",
          "total_volume_btc": "794.1546458445771",
          "sparkline": "https://www.coingecko.com/coins/71121/sparkline.svg",
          "content": null
        }
      }
    },
    {
      "item": {
        "id": "dusk-network",
        "coin_id": 5217,
        "name": "DUSK",
        "symbol": "DUSK",
        "market_cap_rank": 609,
        "thumb": "https://coin-images.coingecko.com/coins/images/5217/standard/image_widget_biddfvxd454b1.png?1696505726",
        "small": "https://coin-images.coingecko.com/coins/images/5217/small/image_widget_biddfvxd454b1.png?1696505726",
        "large": "https://coin-images.coingecko.com/coins/images/5217/large/image_widget_biddfvxd454b1.png?1696505726",
        "slug": "dusk",
        "price_btc": 0.0000012722706098716925,
        "score": 6,
        "data": {
          "price": 0.1213298769801145,
          "price_btc": "0.000001272270609871692",
          "price_change_percentage_24h": {
            "aed": 40.77091348803227,
            "ars": 39.84360580057126,
            "aud": 40.328319765969326,
            "bch": 41.35505285351796,
            "bdt": 40.95393474789982,
            "bhd": 40.9537233564034,
            "bmd": 40.770760163855094,
            "bnb": 39.52603034040051,
            "brl": 40.433460648224916,
            "btc": 40.83249958227695,
            "cad": 40.93015041980082,
            "chf": 40.967233234201544,
            "clp": 40.91067054437145,
            "cny": 40.76167075142145,
            "czk": 40.816042335801164,
            "dkk": 40.983258122889964,
            "dot": 35.18582690245512,
            "eos": 53.66858068976931,
            "eth": 40.79747201031323,
            "eur": 40.88587529355113,
            "gbp": 41.003794033224004,
            "gel": 40.53001343524834,
            "hkd": 40.72556829443671,
            "huf": 40.960748527858,
            "idr": 40.70500326898089,
            "ils": 40.62874994421751,
            "inr": 40.74128516866218,
            "jpy": 40.89110322287157,
            "krw": 40.82750515295394,
            "kwd": 40.721413087377925,
            "lkr": 40.953954281961444,
            "ltc": 37.27514084117178,
            "mmk": 40.78270231611372,
            "mxn": 40.18280992840809,
            "myr": 40.77089893971228,
            "ngn": 40.6587725808185,
            "nok": 40.8485985444643,
            "nzd": 40.90741034558523,
            "php": 40.76218848043375,
            "pkr": 40.95391896100331,
            "pln": 40.86376203469807,
            "rub": 40.813744209640745,
            "sar": 40.7560073055739,
            "sek": 40.68863754190108,
            "sgd": 40.847709162345126,
            "sol": 39.976646339065205,
            "thb": 40.55314921507958,
            "try": 40.7647363346691,
            "twd": 40.8823102358626,
            "uah": 40.95391226504311,
            "usd": 40.770760163855094,
            "vef": 40.770760163855066,
            "vnd": 40.77449058873764,
            "xag": 39.87714945425553,
            "xau": 41.399924967610055,
            "xdr": 41.166178006403634,
            "xlm": 38.61174276155472,
            "xrp": 40.649599675257505,
            "yfi": 32.069841868868245,
            "zar": 40.73053222701862,
            "bits": 40.83249958227694,
            "link": 40.28618444398905,
            "sats": 40.83249958227694
          },
          "market_cap": "$60,607,605",
          "market_cap_btc": "635.6119941157594",
          "total_volume": "$110,592,369",
          "total_volume_btc": "1159.676614658311",
          "sparkline": "https://www.coingecko.com/coins/5217/sparkline.svg",
          "content": {
            "title": "About DUSK",
            "description": "Dusk is a public, permissionless Layer 1 blockchain purpose-built for regulated financial markets. It enables the native issuance, trading, and settlement of real-world assets (RWAs) in full compliance with EU regulations such as MiFID II, MiCA, and the DLT Pilot Regime. Through strategic partnerships - including with NPEX, a Dutch MTF-regulated exchange, and Quantoz, a MiCA-compliant EMI issuing EURQ—Dusk facilitates the creation of secondary markets for digital securities. With privacy-preserving smart contracts, zero-knowledge compliance infrastructure, and institutional custody solutions like Dusk Vault, Dusk provides the complete stack for compliant on-chain finance in Europe."
          }
        }
      }
    },
    {
      "item": {
        "id": "pudgy-penguins",
        "coin_id": 52622,
        "name": "Pudgy Penguins",
        "symbol": "PENGU",
        "market_cap_rank": 119,
        "thumb": "https://coin-images.coingecko.com/coins/images/52622/standard/PUDGY_PENGUINS_PENGU_PFP.png?1733809110",
        "small": "https://coin-images.coingecko.com/coins/images/52622/small/PUDGY_PENGUINS_PENGU_PFP.png?1733809110",
        "large": "https://coin-images.coingecko.com/coins/images/52622/large/PUDGY_PENGUINS_PENGU_PFP.png?1733809110",
        "slug": "pudgy-penguins",
        "price_btc": 1.256929011128681e-7,
        "score": 7,
        "data": {
          "price": 0.011986405798495295,
          "price_btc": "0.0000001256929011128681",
          "price_change_percentage_24h": {
            "aed": -0.22826749907425098,
            "ars": -0.8854991121039857,
            "aud": -0.541956892359401,
            "bch": 0.1706235836348027,
            "bdt": -0.09855072925984512,
            "bhd": -0.09870055350488839,
            "bmd": -0.22837616796336285,
            "bnb": -1.1107116380134359,
            "brl": -0.4674380324657044,
            "btc": -0.18231155112708397,
            "cad": -0.11540793052400714,
            "chf": -0.08912539425925689,
            "clp": -0.1292143403308016,
            "cny": -0.23481831146766255,
            "czk": -0.19628231679399152,
            "dkk": -0.07776771483558505,
            "dot": -4.196188407140369,
            "eos": 8.915502864526301,
            "eth": -0.20731079175684464,
            "eur": -0.14678803556966796,
            "gbp": -0.0632128376827465,
            "gel": -0.3990060062720539,
            "hkd": -0.26040601699330523,
            "huf": -0.09372144589113553,
            "idr": -0.2749815295605651,
            "ils": -0.32902626175767624,
            "inr": -0.24926664358072126,
            "jpy": -0.14308272775595954,
            "krw": -0.18815801683500538,
            "kwd": -0.26335103025551737,
            "lkr": -0.09853688444545486,
            "ltc": -2.703043217109051,
            "mmk": -0.21991213806466875,
            "mxn": -0.6450873489976908,
            "myr": -0.2282778102319649,
            "ngn": -0.30774764394020515,
            "nok": -0.17320802352203496,
            "nzd": -0.13152501427003416,
            "php": -0.23445136975192743,
            "pkr": -0.09856191826169594,
            "pln": -0.16246086237988583,
            "rub": -0.19791111938430558,
            "sar": -0.2388322926953106,
            "sek": -0.28658077903572887,
            "sgd": -0.17383837529487117,
            "sol": -0.7878889437546768,
            "thb": -0.3826084651939494,
            "try": -0.2326455717719068,
            "twd": -0.14931477900865975,
            "uah": -0.09856666404004302,
            "usd": -0.22837616796336285,
            "vef": -0.22837616796340032,
            "vnd": -0.225732220117389,
            "xag": -0.8617249647353517,
            "xau": 0.21754594011884945,
            "xdr": 0.05187720423768608,
            "xlm": -1.752831416473298,
            "xrp": -0.3225177719248232,
            "yfi": -6.383026837330778,
            "zar": -0.2568878175198328,
            "bits": -0.18231155112707248,
            "link": -0.5642576500666968,
            "sats": -0.18231155112707337
          },
          "market_cap": "$753,168,154",
          "market_cap_btc": "7898.979882226221",
          "total_volume": "$114,181,379",
          "total_volume_btc": "1197.338807937793",
          "sparkline": "https://www.coingecko.com/coins/52622/sparkline.svg",
          "content": {
            "title": "PENGU is the official coin of Pudgy Penguins.",
            "description": "Pudgy Penguins has become the face of crypto with one of the most influential communities in the industry. From large companies wearing the Penguin, to being featured in ETF commercials, to garnering millions of followers and over 100 billion views, the Pengu has become a cultural icon making PENGU the world’s social currency."
          }
        }
      }
    },
    {
      "item": {
        "id": "owlto-finance",
        "coin_id": 71561,
        "name": "Owlto Finance",
        "symbol": "OWL",
        "market_cap_rank": 873,
        "thumb": "https://coin-images.coingecko.com/coins/images/71561/standard/owlto.jpg?1768314229",
        "small": "https://coin-images.coingecko.com/coins/images/71561/small/owlto.jpg?1768314229",
        "large": "https://coin-images.coingecko.com/coins/images/71561/large/owlto.jpg?1768314229",
        "slug": "owlto-finance",
        "price_btc": 0.0000010909121869386687,
        "score": 8,
        "data": {
          "price": 0.10403225677342683,
          "price_btc": "0.000001090912186938668",
          "price_change_percentage_24h": {
            "aed": 3.894596357885157,
            "ars": 3.2079108531466054,
            "aud": 3.54576770704826,
            "bch": 4.330708827124353,
            "bdt": 4.029673409299346,
            "bhd": 4.029517393872236,
            "bmd": 3.8944831984752626,
            "bnb": 3.099032220076753,
            "brl": 3.670583327235005,
            "btc": 3.957972110937146,
            "cad": 4.013391605754956,
            "chf": 4.044549321401968,
            "clp": 4.016530739537456,
            "cny": 3.88777484649739,
            "czk": 3.914360726474706,
            "dkk": 4.055440703301402,
            "dot": -0.1610775213238086,
            "eos": 13.562573676786565,
            "eth": 3.9619382820211713,
            "eur": 3.9833078959132733,
            "gbp": 4.055313374029805,
            "gel": 3.716802429250105,
            "hkd": 3.862141790142103,
            "huf": 4.073280347758912,
            "idr": 3.8522071367496475,
            "ils": 3.8025327077684627,
            "inr": 3.8625994617434247,
            "jpy": 3.9667693141262554,
            "krw": 3.93565350810397,
            "kwd": 3.8708746484869474,
            "lkr": 4.029687826222579,
            "ltc": 1.3754904941274122,
            "mmk": 3.903296987189211,
            "mxn": 3.446881960393518,
            "myr": 3.894585620639812,
            "ngn": 3.8118318577373667,
            "nok": 3.968758337950709,
            "nzd": 3.9821055778192607,
            "php": 3.893387106557327,
            "pkr": 4.029661757934827,
            "pln": 3.9721304308270207,
            "rub": 3.9449932927072573,
            "sar": 3.8825423133382873,
            "sek": 3.843461768922863,
            "sgd": 3.952081798513892,
            "sol": 3.323396350146156,
            "thb": 3.7333268973208296,
            "try": 3.889497271240809,
            "twd": 3.975821173156291,
            "uah": 4.029656816046793,
            "usd": 3.8944831984752626,
            "vef": 3.8944831984752453,
            "vnd": 3.8972364020867847,
            "xag": 2.768405821945941,
            "xau": 4.27235089207504,
            "xdr": 4.18631747109848,
            "xlm": 2.3673393636047204,
            "xrp": 3.838347758716997,
            "yfi": -2.97874228364788,
            "zar": 3.855174711512297,
            "bits": 3.957972110937151,
            "link": 3.5766981432478686,
            "sats": 3.9579721109371553
          },
          "market_cap": "$34,402,768",
          "market_cap_btc": "360.7932018736785",
          "total_volume": "$239,714,383",
          "total_volume_btc": "2513.714016258013",
          "sparkline": "https://www.coingecko.com/coins/71561/sparkline.svg",
          "content": null
        }
      }
    },
    {
      "item": {
        "id": "monero",
        "coin_id": 69,
        "name": "Monero",
        "symbol": "XMR",
        "market_cap_rank": 18,
        "thumb": "https://coin-images.coingecko.com/coins/images/69/standard/monero_logo.png?1696501460",
        "small": "https://coin-images.coingecko.com/coins/images/69/small/monero_logo.png?1696501460",
        "large": "https://coin-images.coingecko.com/coins/images/69/large/monero_logo.png?1696501460",
        "slug": "monero",
        "price_btc": 0.00645293037962519,
        "score": 9,
        "data": {
          "price": 615.3684212457658,
          "price_btc": "0.00645293037962519",
          "price_change_percentage_24h": {
            "aed": -13.448445891895947,
            "ars": -14.020503532063252,
            "aud": -13.739044853783833,
            "bch": -13.103676919253735,
            "bdt": -13.33591714512676,
            "bhd": -13.336047117022856,
            "bmd": -13.448540161695616,
            "bnb": -14.118947758514821,
            "brl": -13.635064605697437,
            "btc": -13.40481189563039,
            "cad": -13.349481040169012,
            "chf": -13.323524457187307,
            "clp": -13.346865919489417,
            "cny": -13.454128693818973,
            "czk": -13.431980773618735,
            "dkk": -13.314451164996735,
            "dot": -16.857771515807617,
            "eos": -5.404345338099782,
            "eth": -13.404871500363196,
            "eur": -13.374542900279234,
            "gbp": -13.3145572392944,
            "gel": -13.59656082158235,
            "hkd": -13.475482844485759,
            "huf": -13.299589478184703,
            "idr": -13.483759114097339,
            "ils": -13.525141430199152,
            "inr": -13.475101571640463,
            "jpy": -13.388320709776464,
            "krw": -13.414242379073613,
            "kwd": -13.46820775523135,
            "lkr": -13.335905134809064,
            "ltc": -15.54930936651145,
            "mmk": -13.441197651714226,
            "mxn": -13.82142368148175,
            "myr": -13.448454836781446,
            "ngn": -13.517394579930603,
            "nok": -13.386663712115382,
            "nzd": -13.375544516371102,
            "php": -13.449453283862375,
            "pkr": -13.335926851538286,
            "pln": -13.383854520018104,
            "rub": -13.406461677277914,
            "sar": -13.458487764383916,
            "sek": -13.491044624635789,
            "sgd": -13.400556450101767,
            "sol": -13.93307327669589,
            "thb": -13.58279476981,
            "try": -13.452693792066578,
            "twd": -13.380779870367293,
            "uah": -13.335930968480888,
            "usd": -13.448540161695616,
            "vef": -13.448540161695623,
            "vnd": -13.446246548170876,
            "xag": -14.38664233833683,
            "xau": -13.133749621332512,
            "xdr": -13.205421551844726,
            "xlm": -14.730754358959105,
            "xrp": -13.521313416125281,
            "yfi": -19.194916325682637,
            "zar": -13.48128691422703,
            "bits": -13.404811895630395,
            "link": -13.71535044386201,
            "sats": -13.404811895630395
          },
          "market_cap": "$11,344,943,934",
          "market_cap_btc": "118978.1781413247",
          "total_volume": "$276,368,673",
          "total_volume_btc": "2898.081445365126",
          "sparkline": "https://www.coingecko.com/coins/69/sparkline.svg",
          "content": {
            "title": "What is Monero (XMR)?",
            "description": "Monero (XMR) is the top privacy-centric cryptocurrency based on the CryptoNote protocol, a secure, private and untraceable currency system. Monero uses a special kind of cryptography to ensure that all of its transactions are  remain 100% unlinkable and untraceable. In an increasingly transparent world, you can see why something like Monero can become so desirable."
          }
        }
      }
    },
    {
      "item": {
        "id": "bitcoin",
        "coin_id": 1,
        "name": "Bitcoin",
        "symbol": "BTC",
        "market_cap_rank": 1,
        "thumb": "https://coin-images.coingecko.com/coins/images/1/standard/bitcoin.png?1696501400",
        "small": "https://coin-images.coingecko.com/coins/images/1/small/bitcoin.png?1696501400",
        "large": "https://coin-images.coingecko.com/coins/images/1/large/bitcoin.png?1696501400",
        "slug": "bitcoin",
        "price_btc": 1,
        "score": 10,
        "data": {
          "price": 95352.11325531953,
          "price_btc": "1.0",
          "price_change_percentage_24h": {
            "aed": -0.059926344757603854,
            "ars": -0.7204746535950884,
            "aud": -0.3954775888050036,
            "bch": 0.36392354225063744,
            "bdt": 0.07000929136503073,
            "bhd": 0.06985921432716583,
            "bmd": -0.06003519699972562,
            "bnb": -0.8313681862371785,
            "brl": -0.27541280476357277,
            "btc": 0,
            "cad": 0.05434721939485197,
            "chf": 0.08431898410505421,
            "clp": 0.0573668688515419,
            "cny": -0.06648821009450129,
            "czk": -0.04091426403506528,
            "dkk": 0.09479580915078621,
            "dot": -3.979935976932768,
            "eos": 9.225815986360175,
            "eth": -0.007727508732401526,
            "eur": 0.02540858078619939,
            "gbp": 0.09467332639201446,
            "gel": -0.23095293272401946,
            "hkd": -0.09114559969860841,
            "huf": 0.11195642619501182,
            "idr": -0.10070211203506484,
            "ils": -0.14848579150626873,
            "inr": -0.09070534837517291,
            "jpy": 0.009499504280895287,
            "krw": -0.0204319460035631,
            "kwd": -0.08274513868520826,
            "lkr": 0.07002315953933375,
            "ltc": -2.48092966977344,
            "mmk": -0.05155688605637152,
            "mxn": -0.4905994637684328,
            "myr": -0.059936673312930365,
            "ngn": -0.13954059353250906,
            "nok": 0.011412820223053666,
            "nzd": 0.024252026325416287,
            "php": -0.061089568553670225,
            "pkr": 0.06999808348446256,
            "pln": 0.014656561690277547,
            "rub": -0.011447660064755913,
            "sar": -0.07152157821616184,
            "sek": -0.10911460638399792,
            "sgd": -0.0046289628731145055,
            "sol": -0.6058388678284037,
            "thb": -0.2150574327269839,
            "try": -0.064831345716961,
            "twd": 0.018206823909566714,
            "uah": 0.06999332969871508,
            "usd": -0.06003519699972562,
            "vef": -0.06003519699972242,
            "vnd": -0.05738678811831009,
            "xag": -1.1432508780557136,
            "xau": 0.30344978156654107,
            "xdr": 0.22069103635144743,
            "xlm": -1.5534332098389771,
            "xrp": -0.12780565941927685,
            "yfi": -6.691987966615688,
            "zar": -0.09784749157583654,
            "bits": -0.012002506901187131,
            "link": -0.36636097266085005,
            "sats": -0.012002506901190393
          },
          "market_cap": "$1,904,743,795,032",
          "market_cap_btc": "19977003.0",
          "total_volume": "$27,385,081,662",
          "total_volume_btc": "287161.2121799357",
          "sparkline": "https://www.coingecko.com/coins/1/sparkline.svg",
          "content": {
            "title": "About Bitcoin (BTC)",
            "description": "Bitcoin is the world's first decentralized cryptocurrency that enables peer-to-peer electronic cash transactions without intermediaries like banks or governments."
          }
        }
      }
    },
    {
      "item": {
        "id": "pepe",
        "coin_id": 29850,
        "name": "Pepe",
        "symbol": "PEPE",
        "market_cap_rank": 53,
        "thumb": "https://coin-images.coingecko.com/coins/images/29850/standard/pepe-token.jpeg?1696528776",
        "small": "https://coin-images.coingecko.com/coins/images/29850/small/pepe-token.jpeg?1696528776",
        "large": "https://coin-images.coingecko.com/coins/images/29850/large/pepe-token.jpeg?1696528776",
        "slug": "pepe",
        "price_btc": 6.117989280320718e-11,
        "score": 11,
        "data": {
          "price": 0.000005834275566518903,
          "price_btc": "0.00000000006117989280320718",
          "price_change_percentage_24h": {
            "aed": -0.9426363576590324,
            "ars": -1.5973504441982047,
            "aud": -1.2752238812274845,
            "bch": -0.5375423280960803,
            "bdt": -0.8138483641470599,
            "bhd": -0.8139971156455416,
            "bmd": -0.9427442484753624,
            "bnb": -1.7073938707749963,
            "brl": -1.1562195565512527,
            "btc": -0.892845569860434,
            "cad": -0.8293721025414384,
            "chf": -0.799665060237861,
            "clp": -0.8263791238156925,
            "cny": -0.9491402660220742,
            "czk": -0.9237921991063359,
            "dkk": -0.7892807706289864,
            "dot": -4.837436491962814,
            "eos": 8.263592472340022,
            "eth": -0.8887798410992522,
            "eur": -0.8580551437193357,
            "gbp": -0.7894021715718718,
            "gel": -1.1121523715769566,
            "hkd": -0.9735798718693687,
            "huf": -0.7722717228996324,
            "idr": -0.9830519773325731,
            "ils": -1.030413612564893,
            "inr": -0.9731435090186773,
            "jpy": -0.8738237050077339,
            "krw": -0.9034907889584096,
            "kwd": -0.9652536070295281,
            "lkr": -0.8138346184619146,
            "ltc": -3.339413370580406,
            "mmk": -0.934340821306765,
            "mxn": -1.369505602402702,
            "myr": -0.9426465949885203,
            "ngn": -1.0215474220956506,
            "nok": -0.8719272882240157,
            "nzd": -0.8592014830365304,
            "php": -0.9437893074053325,
            "pkr": -0.8138594730351847,
            "pln": -0.8687121967564234,
            "rub": -0.8945858557644006,
            "sar": -0.9541291774581004,
            "sek": -0.9913901692248501,
            "sgd": -0.8878273839864538,
            "sol": -1.4804329651525503,
            "thb": -1.0963972668837718,
            "try": -0.9474980357219637,
            "twd": -0.8651932918485551,
            "uah": -0.8138641848336563,
            "usd": -0.9427442484753624,
            "vef": -0.9427442484753644,
            "vnd": -0.940119231382191,
            "xag": -2.0163925428683003,
            "xau": -0.5824697121109436,
            "xdr": -0.6644974995592172,
            "xlm": -2.4172372267554096,
            "xrp": -1.0181272393303056,
            "yfi": -7.504119809577273,
            "zar": -0.9802225700033396,
            "bits": -0.8928455698604245,
            "link": -1.2388529862067803,
            "sats": -0.8928455698604352
          },
          "market_cap": "$2,454,832,511",
          "market_cap_btc": "25749.49372190199",
          "total_volume": "$324,651,955",
          "total_volume_btc": "3404.393840747088",
          "sparkline": "https://www.coingecko.com/coins/29850/sparkline.svg",
          "content": {
            "title": "What is Pepe about?",
            "description": "PEPE is a community-driven meme token inspired by the internet character Pepe the Frog, a well-known figure in online meme culture. Launched in April 2023, the project aims to embrace the lighthearted and humorous side of cryptocurrency by creating a token centered around internet culture and community engagement. Rather than focusing on complex use cases or utility, PEPE is built around the idea of shared fun and cultural relevance."
          }
        }
      }
    },
    {
      "item": {
        "id": "smooth-love-potion",
        "coin_id": 10366,
        "name": "Smooth Love Potion",
        "symbol": "SLP",
        "market_cap_rank": 824,
        "thumb": "https://coin-images.coingecko.com/coins/images/10366/standard/SLP.png?1696510368",
        "small": "https://coin-images.coingecko.com/coins/images/10366/small/SLP.png?1696510368",
        "large": "https://coin-images.coingecko.com/coins/images/10366/large/SLP.png?1696510368",
        "slug": "smooth-love-potion",
        "price_btc": 1.0903781806782632e-8,
        "score": 12,
        "data": {
          "price": 0.0010398133253125017,
          "price_btc": "0.00000001090378180678263",
          "price_change_percentage_24h": {
            "aed": 19.17984153186307,
            "ars": 18.39212905685565,
            "aud": 18.779692296138588,
            "bch": 19.65458184066538,
            "bdt": 19.334791472923403,
            "bhd": 19.334612504097958,
            "bmd": 19.17971172414439,
            "bnb": 18.256573232016642,
            "brl": 18.922871117328828,
            "btc": 19.23992471366054,
            "cad": 19.316114247790374,
            "chf": 19.351855968182864,
            "clp": 19.319715219158155,
            "cny": 19.17201642185064,
            "czk": 19.202513686133464,
            "dkk": 19.364349718717882,
            "dot": 14.4852650823078,
            "eos": 30.25641478519111,
            "eth": 19.239842639078695,
            "eur": 19.28160454375085,
            "gbp": 19.364203656430316,
            "gel": 18.97589009470595,
            "hkd": 19.142612163097088,
            "huf": 19.384813978399965,
            "idr": 19.13121589747314,
            "ils": 19.07423323637526,
            "inr": 19.14313716854329,
            "jpy": 19.262632762487595,
            "krw": 19.226939117573743,
            "kwd": 19.152629822437877,
            "lkr": 19.334808010902123,
            "ltc": 16.286992540705402,
            "mmk": 19.189822220542116,
            "mxn": 18.666258219399136,
            "myr": 19.179829214926105,
            "ngn": 19.08490050164729,
            "nok": 19.264914416707438,
            "nzd": 19.280225337469286,
            "php": 19.178454372312245,
            "pkr": 19.334778107379595,
            "pln": 19.268782620721066,
            "rub": 19.237652995753887,
            "sar": 19.166014064706253,
            "sek": 19.121183888222703,
            "sgd": 19.245784381103526,
            "sol": 18.512518853285634,
            "thb": 18.994845685806013,
            "try": 19.173992254234303,
            "twd": 19.27301635472993,
            "uah": 19.33477243842804,
            "usd": 19.17971172414439,
            "vef": 19.17971172414439,
            "vnd": 19.18286998628341,
            "xag": 17.887962894156313,
            "xau": 19.613172302672467,
            "xdr": 19.514481419432432,
            "xlm": 17.414127195773,
            "xrp": 19.07950433884601,
            "yfi": 11.267061192750592,
            "zar": 19.134620069608644,
            "bits": 19.23992471366053,
            "link": 18.812319047313345,
            "sats": 19.23992471366052
          },
          "market_cap": "$37,919,606",
          "market_cap_btc": "397.6754499295704",
          "total_volume": "$28,747,748",
          "total_volume_btc": "301.4571566503808",
          "sparkline": "https://www.coingecko.com/coins/10366/sparkline.svg",
          "content": {
            "title": "What is Smooth Love Potion (SLP)?",
            "description": "Smooth Love Potion (SLP) tokens can be earned as rewards by Axie Infinity players through battle or adventure mode. SLP are tokens that can be used to breed new digital pets, known as Axies. It was formally known as Small Love Potion before the token upgrade to the Ronin blockchain."
          }
        }
      }
    },
    {
      "item": {
        "id": "hyperliquid",
        "coin_id": 50882,
        "name": "Hyperliquid",
        "symbol": "HYPE",
        "market_cap_rank": 30,
        "thumb": "https://coin-images.coingecko.com/coins/images/50882/standard/hyperliquid.jpg?1729431300",
        "small": "https://coin-images.coingecko.com/coins/images/50882/small/hyperliquid.jpg?1729431300",
        "large": "https://coin-images.coingecko.com/coins/images/50882/large/hyperliquid.jpg?1729431300",
        "slug": "hyperliquid",
        "price_btc": 0.0002654424276509234,
        "score": 13,
        "data": {
          "price": 25.313873355478556,
          "price_btc": "0.0002654424276509234",
          "price_change_percentage_24h": {
            "aed": 1.0628155069480711,
            "ars": 0.3948464988426793,
            "aud": 0.7234946296463933,
            "bch": 1.4807031150834342,
            "bdt": 1.1942108595925693,
            "bhd": 1.1940590965665516,
            "bmd": 1.0627054318434639,
            "bnb": 0.28002904612166496,
            "brl": 0.8449082395695079,
            "btc": 1.111428590889083,
            "cad": 1.1783728375450402,
            "chf": 1.2086813095777103,
            "clp": 1.1814264101988494,
            "cny": 1.0561799246268961,
            "czk": 1.0820411722512153,
            "dkk": 1.2192758328551505,
            "dot": -2.908515318923835,
            "eos": 10.453040067621185,
            "eth": 1.1115340664742015,
            "eur": 1.149109097908221,
            "gbp": 1.2191519741066439,
            "gel": 0.889867580513084,
            "hkd": 1.0312455301913035,
            "huf": 1.23662923485799,
            "idr": 1.0215816585547746,
            "ils": 0.9732611700258005,
            "inr": 1.0316907273644615,
            "jpy": 1.1330212964394422,
            "krw": 1.10275359173085,
            "kwd": 1.0397403632499458,
            "lkr": 1.194224883563982,
            "ltc": -1.393179802140047,
            "mmk": 1.0712789894098695,
            "mxn": 0.6273041412016168,
            "myr": 1.0628050623601912,
            "ngn": 0.9823068597019542,
            "nok": 1.1349561068612835,
            "nzd": 1.147939550540262,
            "php": 1.0616392153205512,
            "pkr": 1.1941995258009064,
            "pln": 1.138236289009121,
            "rub": 1.1118388084920807,
            "sar": 1.0510900108890502,
            "sek": 1.0130746569762765,
            "sgd": 1.1187341079558273,
            "sol": 0.49357502002624576,
            "thb": 0.9059416529530953,
            "try": 1.0578554024685793,
            "twd": 1.141826435409253,
            "uah": 1.1941947186104462,
            "usd": 1.0627054318434639,
            "vef": 1.0627054318434643,
            "vnd": 1.0653835933494453,
            "xag": -0.032679257449776206,
            "xau": 1.430273855448085,
            "xdr": 1.3465853860147865,
            "xlm": -0.4403160826915772,
            "xrp": 0.9861076616482908,
            "yfi": -5.6593521469730454,
            "zar": 1.0244683482505168,
            "bits": 1.1114285908890864,
            "link": 0.7434988497080817,
            "sats": 1.1114285908890824
          },
          "market_cap": "$6,036,178,666",
          "market_cap_btc": "63305.45657850987",
          "total_volume": "$103,752,719",
          "total_volume_btc": "1087.955731730865",
          "sparkline": "https://www.coingecko.com/coins/50882/sparkline.svg",
          "content": {
            "title": "What is Hyperliquid about?",
            "description": "Hyperliquid is a performant L1 optimized from the ground up. The vision is a fully on-chain open financial system with user-built applications interfacing with performant native components, all without compromising end-user experience."
          }
        }
      }
    },
    {
      "item": {
        "id": "pi-network",
        "coin_id": 54342,
        "name": "Pi Network",
        "symbol": "PI",
        "market_cap_rank": 66,
        "thumb": "https://coin-images.coingecko.com/coins/images/54342/standard/pi_network.jpg?1739347576",
        "small": "https://coin-images.coingecko.com/coins/images/54342/small/pi_network.jpg?1739347576",
        "large": "https://coin-images.coingecko.com/coins/images/54342/large/pi_network.jpg?1739347576",
        "slug": "pi-network",
        "price_btc": 0.000002147913837846039,
        "score": 14,
        "data": {
          "price": 0.20483071559870503,
          "price_btc": "0.000002147913837846039",
          "price_change_percentage_24h": {
            "aed": -0.20590228040956693,
            "ars": -0.8654857694915856,
            "aud": -0.540963406679236,
            "bch": 0.2022046152856411,
            "bdt": -0.07615643278083044,
            "bhd": -0.07630629061098043,
            "bmd": -0.20601097365832705,
            "bnb": -0.976347638426997,
            "brl": -0.4210739934229899,
            "btc": -0.15574117617254551,
            "cad": -0.0917956281857824,
            "chf": -0.061867641274008234,
            "clp": -0.08878038933379676,
            "cny": -0.21245456125851786,
            "czk": -0.18691796939114363,
            "dkk": -0.05140611904209532,
            "dot": -4.129669791569636,
            "eos": 9.068797405794651,
            "eth": -0.15164520876158302,
            "eur": -0.12069199801586201,
            "gbp": -0.05152842289830107,
            "gel": -0.37667906101358967,
            "hkd": -0.23707593542469368,
            "huf": -0.034270567389953245,
            "idr": -0.24661848918798202,
            "ils": -0.2943323741607091,
            "inr": -0.23663632714759383,
            "jpy": -0.136577837172603,
            "krw": -0.16646556854325467,
            "kwd": -0.22868774441583967,
            "lkr": -0.07614258486285129,
            "ltc": -2.6205051998164413,
            "mmk": -0.19754504642985016,
            "mxn": -0.6359463433350329,
            "myr": -0.2059125938786565,
            "ngn": -0.2854002418532075,
            "nok": -0.13466731588601744,
            "nzd": -0.12184686317313052,
            "php": -0.20706380516065606,
            "pkr": -0.07616762429075304,
            "pln": -0.131428312340016,
            "rub": -0.15749440536395404,
            "sar": -0.2174805774682619,
            "sek": -0.2550186959561105,
            "sgd": -0.15068566779771506,
            "sol": -0.7476987226735969,
            "thb": -0.3608067785348137,
            "try": -0.21080011695450265,
            "twd": -0.12788323575681537,
            "uah": -0.07617237113296052,
            "usd": -0.20601097365832705,
            "vef": -0.20601097365833912,
            "vnd": -0.2033664331347496,
            "xag": -1.2876444723447507,
            "xau": 0.15694308614932204,
            "xdr": 0.07430522122600676,
            "xlm": -1.6914704180729636,
            "xrp": -0.2819546216533983,
            "yfi": -6.816186430010328,
            "zar": -0.2437680382863971,
            "bits": -0.15574117617255379,
            "link": -0.5043220049864738,
            "sats": -0.15574117617254388
          },
          "market_cap": "$1,717,154,196",
          "market_cap_btc": "18008.458320247",
          "total_volume": "$30,712,287",
          "total_volume_btc": "322.0578814494057",
          "sparkline": "https://www.coingecko.com/coins/54342/sparkline.svg",
          "content": {
            "title": "What Is Pi Network?",
            "description": "Pi Network is a social cryptocurrency, developer platform, and ecosystem designed for widespread accessibility and real-world utility. It enables users to mine and transact Pi using a mobile-friendly interface while supporting applications built within its blockchain ecosystem."
          }
        }
      }
    }
  ],
  "categories": [
    {
      "id": 281,
      "name": "Breeding",
      "market_cap_1h_change": 5.864817480218583,
      "slug": "breeding",
      "coins_count": "19",
      "data": {
        "market_cap": 345686739.554587,
        "market_cap_btc": 3625.352480473891,
        "total_volume": 742594243.9243623,
        "total_volume_btc": 7787.8772198946435,
        "market_cap_change_percentage_24h": {
          "aed": 84.45178926415653,
          "ars": 82.85317566889795,
          "aud": 84.07859261548765,
          "bch": 82.78255687858139,
          "bdt": 84.72608024693731,
          "bhd": 84.70406270471972,
          "bmd": 84.45158836385609,
          "bnb": 82.28512289593051,
          "brl": 84.49639636535134,
          "btc": 84.85521927031601,
          "cad": 84.80068630731373,
          "chf": 84.3179763690788,
          "clp": 84.81314072432463,
          "cny": 84.51645779304354,
          "czk": 84.47002112247303,
          "dkk": 84.59980688568155,
          "dot": 77.54531065577297,
          "eos": 144.09705959356646,
          "eth": 85.38657663226277,
          "eur": 84.48648989385443,
          "gbp": 84.4377667367414,
          "gel": 84.13613850457257,
          "hkd": 84.45336255665131,
          "huf": 84.5494317762711,
          "idr": 84.65142875430881,
          "ils": 84.5612651836459,
          "inr": 85.16164869164695,
          "jpy": 83.96902086428193,
          "krw": 84.90839233313564,
          "kwd": 84.34384795009218,
          "lkr": 84.9207380869647,
          "ltc": 78.92632054301303,
          "mmk": 84.4672361372291,
          "mxn": 84.13561218888847,
          "myr": 84.58824949875437,
          "ngn": 83.91111500810872,
          "nok": 84.17053102208014,
          "nzd": 84.15076561266348,
          "php": 84.31319152264987,
          "pkr": 84.69862187266514,
          "pln": 84.96854345086695,
          "rub": 83.35260316721171,
          "sar": 84.42060228180924,
          "sek": 84.53391111524536,
          "sgd": 84.53436077534025,
          "sol": 82.50574377697701,
          "thb": 84.51249850779703,
          "try": 84.45587183989015,
          "twd": 84.70705772422377,
          "uah": 84.16495496265347,
          "usd": 84.45158836385609,
          "vef": 84.45158836385615,
          "vnd": 84.50494098527732,
          "xag": 87.0551391920028,
          "xau": 85.30159568350523,
          "xdr": 84.96970341161594,
          "xlm": 84.6573721618885,
          "xrp": 86.03322436805317,
          "yfi": 76.4500925218207,
          "zar": 85.05872213319734,
          "bits": 84.85521927031601,
          "link": 84.67226606068475,
          "sats": 84.85521927031601
        },
        "sparkline": "https://www.coingecko.com/categories/281/sparkline.svg"
      }
    },
    {
      "id": 76,
      "name": "Axie Infinity Ecosystem",
      "market_cap_1h_change": 5.069071888451418,
      "slug": "axie-infinity",
      "coins_count": "2",
      "data": {
        "market_cap": 378332791.7821763,
        "market_cap_btc": 3967.8180546702943,
        "total_volume": 770985100.3382792,
        "total_volume_btc": 8085.814043751445,
        "market_cap_change_percentage_24h": {
          "aed": 77.59738686149777,
          "ars": 76.04908379234621,
          "aud": 77.2511227854466,
          "bch": 75.96870186941266,
          "bdt": 77.86148493273828,
          "bhd": 77.84028558314917,
          "bmd": 77.59719342684184,
          "bnb": 75.54114913954402,
          "brl": 77.59071057030079,
          "btc": 77.99257241062328,
          "cad": 77.93908301542048,
          "chf": 77.47826594533352,
          "clp": 77.94531016069942,
          "cny": 77.65965224687741,
          "czk": 77.6396581390712,
          "dkk": 77.75067454737405,
          "dot": 70.91771661506677,
          "eos": 135.03509247090471,
          "eth": 78.50639410483072,
          "eur": 77.63925266466289,
          "gbp": 77.58982625048067,
          "gel": 77.29346598175682,
          "hkd": 77.59491579513626,
          "huf": 77.68907864788765,
          "idr": 77.78960755996235,
          "ils": 77.70279455259762,
          "inr": 78.2804963256821,
          "jpy": 77.1554555506322,
          "krw": 78.03702212991736,
          "kwd": 77.49345674843833,
          "lkr": 78.04890910389369,
          "ltc": 72.31471117499227,
          "mmk": 77.61225971420252,
          "mxn": 77.29044890300088,
          "myr": 77.72877610511398,
          "ngn": 77.07680457058885,
          "nok": 77.33263148606171,
          "nzd": 77.38099285011799,
          "php": 77.46393954274475,
          "pkr": 77.83504693754371,
          "pln": 78.10043614183105,
          "rub": 76.5466946969259,
          "sar": 77.56735881681969,
          "sek": 77.70392865861612,
          "sgd": 77.68806419420244,
          "sol": 75.7305566506941,
          "thb": 77.71243640973161,
          "try": 77.60075959969906,
          "twd": 77.84373247043528,
          "uah": 77.3212115930853,
          "usd": 77.59719342684184,
          "vef": 77.59719342684186,
          "vnd": 77.64856341454669,
          "xag": 80.82736722487994,
          "xau": 78.48964163501692,
          "xdr": 78.09605483091313,
          "xlm": 77.77602114289044,
          "xrp": 79.12117772024394,
          "yfi": 69.91725852534684,
          "zar": 78.27652172853868,
          "bits": 77.99257241062327,
          "link": 77.81305475038418,
          "sats": 77.99257241062327
        },
        "sparkline": "https://www.coingecko.com/categories/76/sparkline.svg"
      }
    },
    {
      "id": 277,
      "name": "Card Games",
      "market_cap_1h_change": 4.557708541676224,
      "slug": "card-games",
      "coins_count": "43",
      "data": {
        "market_cap": 461583039.3926323,
        "market_cap_btc": 4840.802453003877,
        "total_volume": 757545094.0697532,
        "total_volume_btc": 7944.672651879177,
        "market_cap_change_percentage_24h": {
          "aed": 53.56108527647816,
          "ars": 52.23019637805669,
          "aud": 53.25038900934101,
          "bch": 52.17140433204194,
          "bdt": 53.78943991139605,
          "bhd": 53.771109714158385,
          "bmd": 53.56091802156406,
          "bnb": 51.757277136344904,
          "brl": 53.59822189032094,
          "btc": 53.89695162847232,
          "cad": 53.85155146718691,
          "chf": 53.44968243525826,
          "clp": 53.861920104977365,
          "cny": 53.61492356950173,
          "czk": 53.57626378984938,
          "dkk": 53.68431393526267,
          "dot": 47.81125571519747,
          "eos": 103.21738018113791,
          "eth": 54.33932095162016,
          "eur": 53.589974485834425,
          "gbp": 53.54941114451785,
          "gel": 53.29829751278431,
          "hkd": 53.562395084878055,
          "huf": 53.642375299140745,
          "idr": 53.727290532031006,
          "ils": 53.65222692967377,
          "inr": 54.152062379568534,
          "jpy": 53.159167573659005,
          "krw": 53.94121963620828,
          "kwd": 53.4712212236543,
          "lkr": 53.95149780897152,
          "ltc": 48.96098366258226,
          "mmk": 53.57394521458235,
          "mxn": 53.29785934079384,
          "myr": 53.67469209919058,
          "ngn": 53.110959387914114,
          "nok": 53.32693021043893,
          "nzd": 53.31047497444978,
          "php": 53.445698921661375,
          "pkr": 53.76658007485023,
          "pln": 53.99129706270686,
          "rub": 52.64598322926554,
          "sar": 53.535121273229095,
          "sek": 53.62945393057702,
          "sgd": 53.6298282847237,
          "sol": 51.9409499652359,
          "thb": 53.61162735783685,
          "try": 53.56448413079604,
          "twd": 53.773603148606995,
          "uah": 53.32228799069932,
          "usd": 53.56091802156406,
          "vef": 53.560918021564085,
          "vnd": 53.60533551667474,
          "xag": 55.72844424799776,
          "xau": 54.26857202166345,
          "xdr": 53.99226276128971,
          "xlm": 53.73223857900749,
          "xrp": 54.87767261790485,
          "yfi": 46.89945710410711,
          "zar": 54.06637324593449,
          "bits": 53.89695162847234,
          "link": 53.74463815112481,
          "sats": 53.89695162847234
        },
        "sparkline": "https://www.coingecko.com/categories/277/sparkline.svg"
      }
    },
    {
      "id": 316,
      "name": "Gaming Governance Token",
      "market_cap_1h_change": 2.3785859902295927,
      "slug": "gaming-governance-token",
      "coins_count": "64",
      "data": {
        "market_cap": 974852809.6843408,
        "market_cap_btc": 10223.905151575125,
        "total_volume": 908095415.716601,
        "total_volume_btc": 9523.777647902538,
        "market_cap_change_percentage_24h": {
          "aed": 25.635954910585923,
          "ars": 24.540654253175155,
          "aud": 25.39100075548997,
          "bch": 24.479125325901876,
          "bdt": 25.822783185239683,
          "bhd": 25.807786339981,
          "bmd": 25.63581807102914,
          "bnb": 24.177588201829444,
          "brl": 25.631231968235202,
          "btc": 25.91593643541097,
          "cad": 25.87767762591416,
          "chf": 25.55168638436158,
          "clp": 25.88208283343053,
          "cny": 25.680002693542065,
          "czk": 25.665858460503472,
          "dkk": 25.744393695251865,
          "dot": 20.907550313087697,
          "eos": 66.26909405738246,
          "eth": 26.27222794300997,
          "eur": 25.66557161977129,
          "gbp": 25.63060638265079,
          "gel": 25.420955182164835,
          "hkd": 25.634206828660545,
          "huf": 25.700819520049684,
          "idr": 25.771935689537496,
          "ils": 25.71052242624751,
          "inr": 26.119200251961338,
          "jpy": 25.32332383404438,
          "krw": 25.94696172063175,
          "kwd": 25.562432663277402,
          "lkr": 25.955370804531615,
          "ltc": 21.902300023142036,
          "mmk": 25.64647626500912,
          "mxn": 25.41882084011602,
          "myr": 25.728902297810592,
          "ngn": 25.267684552650536,
          "nok": 25.448661645755667,
          "nzd": 25.48287344504711,
          "php": 25.541551599714808,
          "pkr": 25.804080416967643,
          "pln": 25.99182206504494,
          "rub": 24.89267419150646,
          "sar": 25.614712469275887,
          "sek": 25.711324715600554,
          "sgd": 25.700101875158055,
          "sol": 24.312736227188335,
          "thb": 25.717343269445436,
          "try": 25.638340853262665,
          "twd": 25.81022473720809,
          "uah": 25.44058298432697,
          "usd": 25.63581807102914,
          "vef": 25.635818071029163,
          "vnd": 25.672158231056823,
          "xag": 27.920907828347207,
          "xau": 26.267153840230307,
          "xdr": 25.988722637791778,
          "xlm": 25.76524956785796,
          "xrp": 26.716500287989586,
          "yfi": 20.193019269545434,
          "zar": 26.11638854219282,
          "bits": 25.91593643541096,
          "link": 25.7869178520428,
          "sats": 25.915936435410963
        },
        "sparkline": "https://www.coingecko.com/categories/316/sparkline.svg"
      }
    },
    {
      "id": 317,
      "name": "Gaming Utility Token",
      "market_cap_1h_change": 1.3804203755339317,
      "slug": "gaming-utility-token",
      "coins_count": "136",
      "data": {
        "market_cap": 1578953758.4504087,
        "market_cap_btc": 16559.107624803324,
        "total_volume": 1106802225.2680404,
        "total_volume_btc": 11607.469230493569,
        "market_cap_change_percentage_24h": {
          "aed": 19.50667998649927,
          "ars": 18.47093506847609,
          "aud": 19.264885137870092,
          "bch": 18.42518101421039,
          "bdt": 19.68439365809409,
          "bhd": 19.670128448835953,
          "bmd": 19.50654982279628,
          "bnb": 18.102892550562412,
          "brl": 19.53558101580824,
          "btc": 19.768063087391877,
          "cad": 19.7327310725373,
          "chf": 19.41998234646055,
          "clp": 19.74080031401269,
          "cny": 19.548578854586847,
          "czk": 19.518492443651787,
          "dkk": 19.60258089696764,
          "dot": 15.03195880228959,
          "eos": 58.150968894734746,
          "eth": 20.11233057574733,
          "eur": 19.529162593283317,
          "gbp": 19.497594763183816,
          "gel": 19.30216923350749,
          "hkd": 19.507699325826096,
          "huf": 19.569942763699245,
          "idr": 19.636026808004647,
          "ils": 19.5776096518001,
          "inr": 19.966599317045887,
          "jpy": 19.193893383010245,
          "krw": 19.802514020221736,
          "kwd": 19.43674459509606,
          "lkr": 19.810512858606153,
          "ltc": 15.926717846433283,
          "mmk": 19.5166880461903,
          "mxn": 19.301828232532202,
          "myr": 19.59509284306208,
          "ngn": 19.156376063982655,
          "nok": 19.324452213792494,
          "nzd": 19.311646165841516,
          "php": 19.416882234972103,
          "pkr": 19.66660332296,
          "pln": 19.841486048664606,
          "rub": 18.794515134874697,
          "sar": 19.486473878800375,
          "sek": 19.559886896647043,
          "sgd": 19.560178232314087,
          "sol": 18.245833256829066,
          "thb": 19.54601362582535,
          "try": 19.509325095411825,
          "twd": 19.67206892791102,
          "uah": 19.320839473834017,
          "usd": 19.50654982279628,
          "vef": 19.506549822796305,
          "vnd": 19.541117092000164,
          "xag": 21.193395566549512,
          "xau": 20.05727125055113,
          "xdr": 19.842237589533802,
          "xlm": 19.63987755355985,
          "xrp": 20.531294925908373,
          "yfi": 14.322364801755397,
          "zar": 19.89991299574851,
          "bits": 19.768063087391877,
          "link": 19.64952734012083,
          "sats": 19.768063087391887
        },
        "sparkline": "https://www.coingecko.com/categories/317/sparkline.svg"
      }
    },
    {
      "id": 13,
      "name": "Entertainment",
      "market_cap_1h_change": 1.088192088111287,
      "slug": "entertainment",
      "coins_count": "122",
      "data": {
        "market_cap": 809753972.1600968,
        "market_cap_btc": 8492.836478974923,
        "total_volume": 222329438.88323843,
        "total_volume_btc": 2331.828720593512,
        "market_cap_change_percentage_24h": {
          "aed": 8.605632546941923,
          "ars": 7.658803107775129,
          "aud": 8.393882646380963,
          "bch": 7.613031381724052,
          "bdt": 8.767135700723573,
          "bhd": 8.754171721847548,
          "bmd": 8.605514256388625,
          "bnb": 7.349454904176625,
          "brl": 8.601549813286194,
          "btc": 8.853153492019409,
          "cad": 8.814589038878232,
          "chf": 8.53278686673114,
          "clp": 8.81839710758883,
          "cny": 8.643709523661267,
          "czk": 8.63148258291693,
          "dkk": 8.699372136135551,
          "dot": 4.5289267145590975,
          "eos": 43.738082158418194,
          "eth": 9.16190332557003,
          "eur": 8.631234624287764,
          "gbp": 8.601009027663533,
          "gel": 8.419776662619546,
          "hkd": 8.60412142265123,
          "huf": 8.661704568249357,
          "idr": 8.72318073227449,
          "ils": 8.670092217039086,
          "inr": 9.023372564222724,
          "jpy": 8.33537953023354,
          "krw": 8.874481471244454,
          "kwd": 8.542076456005226,
          "lkr": 8.881750679145469,
          "ltc": 5.3889432760654215,
          "mmk": 8.614727700898463,
          "mxn": 8.417931636898627,
          "myr": 8.685980643076551,
          "ngn": 8.287282316704674,
          "nok": 8.443727433766727,
          "nzd": 8.473301723270614,
          "php": 8.524025881883514,
          "pkr": 8.75096814757361,
          "pln": 8.913260864330947,
          "rub": 7.963105710472056,
          "sar": 8.587269580886863,
          "sek": 8.670785753716064,
          "sgd": 8.66108420222867,
          "sol": 7.467229615692575,
          "thb": 8.675988474926017,
          "try": 8.607695068087311,
          "twd": 8.75627958717506,
          "uah": 8.436743858601336,
          "usd": 8.605514256388625,
          "vef": 8.605514256388634,
          "vnd": 8.636928401085326,
          "xag": 10.580853391564483,
          "xau": 9.151270609435807,
          "xdr": 8.91058157353709,
          "xlm": 8.718304924235792,
          "xrp": 9.54690550028247,
          "yfi": 3.945603916070877,
          "zar": 9.020941989964255,
          "bits": 8.853153492019407,
          "link": 8.762955399491243,
          "sats": 8.853153492019404
        },
        "sparkline": "https://www.coingecko.com/categories/13/sparkline.svg"
      }
    }
  ]
}