{
  "coins": [
    {
      "item": {
        "id": "hyperliquid",
        "coin_id": 50882,
        "name": "Hyperliquid",
        "symbol": "HYPE",
        "market_cap_rank": 28,
        "thumb": "https://coin-images.coingecko.com/coins/images/50882/standard/hyperliquid.jpg?1729431300",
        "small": "https://coin-images.coingecko.com/coins/images/50882/small/hyperliquid.jpg?1729431300",
        "large": "https://coin-images.coingecko.com/coins/images/50882/large/hyperliquid.jpg?1729431300",
        "slug": "hyperliquid",
        "price_btc": 0.00031104253762016495,
        "score": 0,
        "data": {
          "price": 27.342563503097512,
          "price_btc": "0.0003110425376201649",
          "price_change_percentage_24h": {
            "aed": 23.45864270764304,
            "ars": 23.738261715763016,
            "aud": 23.622316575147494,
            "bch": 20.987916506308686,
            "bdt": 24.503558423383698,
            "bhd": 23.483205595649363,
            "bmd": 23.45864270764303,
            "bnb": 21.792415338229254,
            "brl": 22.49031803006601,
            "btc": 23.088687659919575,
            "cad": 23.839441363030318,
            "chf": 23.609847121868196,
            "clp": 22.774990528898172,
            "cny": 23.45864270764301,
            "czk": 23.221842387807516,
            "dkk": 23.330337409207445,
            "dot": 23.02204921885918,
            "eos": 22.93431844443341,
            "eth": 22.492784954965494,
            "eur": 23.340526237244056,
            "gbp": 23.386762107605737,
            "gel": 23.37842379938087,
            "hkd": 23.52438602087102,
            "huf": 23.39237999423751,
            "idr": 23.498042755107058,
            "ils": 22.46599360256986,
            "inr": 23.647204716340152,
            "jpy": 24.191961421798887,
            "krw": 24.458560811754936,
            "kwd": 23.46186215709462,
            "lkr": 24.38834052531491,
            "ltc": 21.674989634430236,
            "mmk": 23.458642707642984,
            "mxn": 23.22055799704563,
            "myr": 23.0386095230278,
            "ngn": 23.422782298363572,
            "nok": 23.71252215199583,
            "nzd": 23.703903633790997,
            "php": 23.70155214233993,
            "pkr": 24.565177822739884,
            "pln": 23.239625051852485,
            "rub": 24.06186535753112,
            "sar": 23.46124361687926,
            "sek": 23.587630997620643,
            "sgd": 23.449494883696897,
            "sol": 21.99990491185651,
            "thb": 23.61269145640277,
            "try": 23.515277800979455,
            "twd": 23.618506612506586,
            "uah": 24.450194065646762,
            "usd": 23.45864270764303,
            "vef": 23.458642707643026,
            "vnd": 23.263242599501375,
            "xag": 20.560479962932583,
            "xau": 23.584332341348933,
            "xdr": 23.22054663933571,
            "xlm": 24.366296966420894,
            "xrp": 23.226866683861537,
            "yfi": 21.81052029783628,
            "zar": 23.76687388061147,
            "bits": 23.088687659919554,
            "link": 22.498571999169453,
            "sats": 23.08868765991956
          },
          "market_cap": "$6,531,299,009",
          "market_cap_btc": "74305.98323696367",
          "total_volume": "$490,599,035",
          "total_volume_btc": "5580.938631115486",
          "sparkline": "https://www.coingecko.com/coins/50882/sparkline.svg",
          "content": {
            "title": "What is Hyperliquid about?",
            "description": "Hyperliquid is a performant L1 optimized from the ground up. The vision is a fully on-chain open financial system with user-built applications interfacing with performant native components, all without compromising end-user experience."
          }
        }
      }
    },
    {
      "item": {
        "id": "river",
        "coin_id": 69318,
        "name": "River",
        "symbol": "RIVER",
        "market_cap_rank": 88,
        "thumb": "https://coin-images.coingecko.com/coins/images/69318/standard/river-token.png?1758523089",
        "small": "https://coin-images.coingecko.com/coins/images/69318/small/river-token.png?1758523089",
        "large": "https://coin-images.coingecko.com/coins/images/69318/large/river-token.png?1758523089",
        "slug": "river",
        "price_btc": 0.0006520063493510224,
        "score": 1,
        "data": {
          "price": 57.315392125959015,
          "price_btc": "0.0006520063493510224",
          "price_change_percentage_24h": {
            "aed": -33.34226909944577,
            "ars": -33.18646277543258,
            "aud": -33.24692028159459,
            "bch": -34.6636409057488,
            "bdt": -32.77809870954009,
            "bhd": -33.329007116785384,
            "bmd": -33.34226909944578,
            "bnb": -34.225816809089224,
            "brl": -33.857077803585334,
            "btc": -33.495593828925344,
            "cad": -33.126010414116735,
            "chf": -33.19782853493854,
            "clp": -33.71138625447772,
            "cny": -33.33939418652849,
            "czk": -33.442378424271396,
            "dkk": -33.387657179873095,
            "dot": -33.59808970263149,
            "eos": -33.58375173374217,
            "eth": -33.86757452561625,
            "eur": -33.382507174386845,
            "gbp": -33.36550571183126,
            "gel": -33.38558085375317,
            "hkd": -33.307577040397284,
            "huf": -33.3759553837149,
            "idr": -33.30801539173631,
            "ils": -33.86962301939842,
            "inr": -33.243020431806684,
            "jpy": -32.90083675168901,
            "krw": -32.789083548089735,
            "kwd": -33.3405308558487,
            "lkr": -32.840307101564804,
            "ltc": -34.33765129774966,
            "mmk": -33.3422690994458,
            "mxn": -33.461118565555836,
            "myr": -33.552307323861456,
            "ngn": -33.36163083434993,
            "nok": -33.199794117945096,
            "nzd": -33.202147695368296,
            "php": -33.213385347543806,
            "pkr": -32.7448291931218,
            "pln": -33.45986510649266,
            "rub": -33.1365518094518,
            "sar": -33.340384859851596,
            "sek": -33.26912188762427,
            "sgd": -33.33454373782879,
            "sol": -34.11049065633967,
            "thb": -33.204786186856836,
            "try": -33.291542856873676,
            "twd": -33.31048494496285,
            "uah": -32.80691116786374,
            "usd": -33.34226909944578,
            "vef": -33.34226909944577,
            "vnd": -33.44776943170918,
            "xag": -34.818455113914645,
            "xau": -33.18938439554546,
            "xdr": -33.47082181395515,
            "xlm": -32.85585647112564,
            "xrp": -33.45675220878855,
            "yfi": -34.24976615939914,
            "zar": -33.18276939828581,
            "bits": -33.49559382892534,
            "link": -33.88009778396122,
            "sats": -33.495593828925344
          },
          "market_cap": "$1,133,649,636",
          "market_cap_btc": "12896.81679247843",
          "total_volume": "$62,018,976",
          "total_volume_btc": "705.5132055033326",
          "sparkline": "https://www.coingecko.com/coins/69318/sparkline.svg",
          "content": null
        }
      }
    },
    {
      "item": {
        "id": "pudgy-penguins",
        "coin_id": 52622,
        "name": "Pudgy Penguins",
        "symbol": "PENGU",
        "market_cap_rank": 138,
        "thumb": "https://coin-images.coingecko.com/coins/images/52622/standard/PUDGY_PENGUINS_PENGU_PFP.png?1733809110",
        "small": "https://coin-images.coingecko.com/coins/images/52622/small/PUDGY_PENGUINS_PENGU_PFP.png?1733809110",
        "large": "https://coin-images.coingecko.com/coins/images/52622/large/PUDGY_PENGUINS_PENGU_PFP.png?1733809110",
        "slug": "pudgy-penguins",
        "price_btc": 1.0842015969066563e-7,
        "score": 2,
        "data": {
          "price": 0.009530802841436856,
          "price_btc": "0.0000001084201596906656",
          "price_change_percentage_24h": {
            "aed": 0.7773332915218876,
            "ars": 1.005581856044632,
            "aud": 0.9109376754261221,
            "bch": -1.216426475051663,
            "bdt": 1.6302814289488543,
            "bhd": 0.797383587693314,
            "bmd": 0.7773332915218631,
            "bnb": -0.551164925744236,
            "brl": -0.013094795377413773,
            "btc": 0.49641036415860534,
            "cad": 1.088173198467901,
            "chf": 0.9007590583481391,
            "clp": 0.21927885351873416,
            "cny": 0.7773332915218683,
            "czk": 0.5840369435933304,
            "dkk": 0.6725997099764238,
            "dot": 0.44515596220492304,
            "eos": 0.3703748013296935,
            "eth": 0.039939516468636596,
            "eur": 0.6809166888154624,
            "gbp": 0.7186582969789248,
            "gel": 0.7118518681325103,
            "hkd": 0.830998516114982,
            "huf": 0.7232440887960301,
            "idr": 0.8094949257979492,
            "ils": -0.03295044001387941,
            "inr": 0.9312534706185291,
            "jpy": 1.3759297351940643,
            "krw": 1.5935505917633894,
            "kwd": 0.7799612770827161,
            "lkr": 1.5362308848948185,
            "ltc": -0.6561027801130225,
            "mmk": 0.7773332915218293,
            "mxn": 0.5829885157713104,
            "myr": 0.43446686021251757,
            "ngn": 0.7480610077946122,
            "nok": 0.9845710580992706,
            "nzd": 0.9775358982873772,
            "php": 0.9756164130857203,
            "pkr": 1.6805803680101372,
            "pln": 0.5985526504079469,
            "rub": 1.2697343798825016,
            "sar": 0.7794563725084322,
            "sek": 0.8826243882380321,
            "sgd": 0.7698660678225323,
            "sol": -0.39301176831192536,
            "thb": 0.9030808435475681,
            "try": 0.8235636205777217,
            "twd": 0.9078276633081407,
            "uah": 1.5867209495235488,
            "usd": 0.7773332915218631,
            "vef": 0.7773332915218764,
            "vnd": 0.6178312802287595,
            "xag": -1.5883910227198879,
            "xau": 0.8799317474052717,
            "xdr": 0.5829792446526789,
            "xlm": 1.542849771012627,
            "xrp": 0.613207705969053,
            "yfi": -0.5440462737433973,
            "zar": 1.0289375127235982,
            "bits": 0.49641036415861783,
            "link": 0.02095787894153046,
            "sats": 0.49641036415860906
          },
          "market_cap": "$599,127,725",
          "market_cap_btc": "6816.073513038787",
          "total_volume": "$102,738,243",
          "total_volume_btc": "1168.72596562845",
          "sparkline": "https://www.coingecko.com/coins/52622/sparkline.svg",
          "content": {
            "title": "PENGU is the official coin of Pudgy Penguins.",
            "description": "Pudgy Penguins has become the face of crypto with one of the most influential communities in the industry. From large companies wearing the Penguin, to being featured in ETF commercials, to garnering millions of followers and over 100 billion views, the Pengu has become a cultural icon making PENGU the world’s social currency."
          }
        }
      }
    },
    {
      "item": {
        "id": "ethereum",
        "coin_id": 279,
        "name": "Ethereum",
        "symbol": "ETH",
        "market_cap_rank": 2,
        "thumb": "https://coin-images.coingecko.com/coins/images/279/standard/ethereum.png?1696501628",
        "small": "https://coin-images.coingecko.com/coins/images/279/small/ethereum.png?1696501628",
        "large": "https://coin-images.coingecko.com/coins/images/279/large/ethereum.png?1696501628",
        "slug": "ethereum",
        "price_btc": 0.03309612433968819,
        "score": 3,
        "data": {
          "price": 2909.3540979575287,
          "price_btc": "0.03309612433968819",
          "price_change_percentage_24h": {
            "aed": 0.7190012635683927,
            "ars": 0.9471177130489091,
            "aud": 0.8525283144612967,
            "bch": -1.264278218067009,
            "bdt": 1.5714556967766455,
            "bhd": 0.7390399542091273,
            "bmd": 0.7190012635683792,
            "bnb": -0.6449015715005698,
            "brl": -0.07096930702486001,
            "btc": 0.4369010189929656,
            "cad": 1.0296612498760243,
            "chf": 0.842355588979751,
            "clp": 0.16126983914397203,
            "cny": 0.7190012635683666,
            "czk": 0.5258167996082515,
            "dkk": 0.6143283040101221,
            "dot": 0.41208635671209926,
            "eos": 0.3109400886189302,
            "eth": 0,
            "eur": 0.6226404688078633,
            "gbp": 0.6603602313392934,
            "gel": 0.6535577421962017,
            "hkd": 0.7726354256072743,
            "huf": 0.6649433688041885,
            "idr": 0.7511442820179872,
            "ils": -0.09081345879900699,
            "inr": 0.872832350446647,
            "jpy": 1.3172512271011743,
            "krw": 1.5347461201678954,
            "kwd": 0.7216277279962363,
            "lkr": 1.4774595911442625,
            "ltc": -0.6952396135407275,
            "mmk": 0.7190012635683468,
            "mxn": 0.5247689786381707,
            "myr": 0.3763332905194552,
            "ngn": 0.689745923251063,
            "nok": 0.926119076592766,
            "nzd": 0.9190879888784732,
            "php": 0.9171696147149718,
            "pkr": 1.6217255217601934,
            "pln": 0.5403241044281836,
            "rub": 1.211117339882033,
            "sar": 0.7211231156712811,
            "sek": 0.8242314155959554,
            "sgd": 0.7115383620543364,
            "sol": -0.45355592388411914,
            "thb": 0.8446760302813674,
            "try": 0.7652048335430203,
            "twd": 0.8494201024833914,
            "uah": 1.5279204310677934,
            "usd": 0.7190012635683792,
            "vef": 0.7190012635683908,
            "vnd": 0.5595915753748837,
            "xag": -1.6453537199685182,
            "xau": 0.8215403333200098,
            "xdr": 0.5247597128858373,
            "xlm": 1.4970953915840006,
            "xrp": 0.5652648653574528,
            "yfi": -0.5636943682543537,
            "zar": 0.9704598509853718,
            "bits": 0.43690101899295497,
            "link": -0.026075651393416884,
            "sats": 0.4369010189929603
          },
          "market_cap": "$351,194,667,423",
          "market_cap_btc": "3995113.219214157",
          "total_volume": "$25,045,055,542",
          "total_volume_btc": "284906.6302730897",
          "sparkline": "https://www.coingecko.com/coins/279/sparkline.svg",
          "content": {
            "title": "About Ethereum",
            "description": "Ethereum is a blockchain platform that enables developers to build and deploy smart contracts and decentralized applications, operating through thousands of independent nodes worldwide rather than through a central authority."
          }
        }
      }
    },
    {
      "item": {
        "id": "pump-fun",
        "coin_id": 67164,
        "name": "Pump.fun",
        "symbol": "PUMP",
        "market_cap_rank": 59,
        "thumb": "https://coin-images.coingecko.com/coins/images/67164/standard/pump.jpg?1751949376",
        "small": "https://coin-images.coingecko.com/coins/images/67164/small/pump.jpg?1751949376",
        "large": "https://coin-images.coingecko.com/coins/images/67164/large/pump.jpg?1751949376",
        "slug": "pump-fun",
        "price_btc": 3.458808659716198e-8,
        "score": 4,
        "data": {
          "price": 0.0030405068112851767,
          "price_btc": "0.00000003458808659716198",
          "price_change_percentage_24h": {
            "aed": 21.438134311656967,
            "ars": 21.71317711076316,
            "aud": 21.599129513527032,
            "bch": 19.039053745257988,
            "bdt": 22.465949070101725,
            "bhd": 21.462295206571838,
            "bmd": 21.438134311656963,
            "bnb": 19.84030419321815,
            "brl": 20.485657112216582,
            "btc": 21.164325989321505,
            "cad": 21.812700864831605,
            "chf": 21.586864133729268,
            "clp": 20.765670697250723,
            "cny": 21.438134311656952,
            "czk": 21.205209435645447,
            "dkk": 21.3119288413667,
            "dot": 20.981719972214165,
            "eos": 21.003711170954666,
            "eth": 20.45662188811118,
            "eur": 21.321950920343514,
            "gbp": 21.367430100349544,
            "gel": 21.359228255813285,
            "hkd": 21.50280167820805,
            "huf": 21.372956045365402,
            "idr": 21.47688954297079,
            "ils": 20.461730775197555,
            "inr": 21.623610338576093,
            "jpy": 22.159451625292004,
            "krw": 22.421687883644232,
            "kwd": 21.441301072009573,
            "lkr": 22.352616813453494,
            "ltc": 19.659030186212668,
            "mmk": 21.438134311656935,
            "mxn": 21.203946065058908,
            "myr": 21.024975336554302,
            "ngn": 21.402860789260888,
            "nok": 21.687858797412858,
            "nzd": 21.679381328777385,
            "php": 21.677068321535472,
            "pkr": 22.52656001422932,
            "pln": 21.22270107087933,
            "rub": 22.031484696614758,
            "sar": 21.44069265474446,
            "sek": 21.565011595736838,
            "sgd": 21.429136199830534,
            "sol": 20.0488000754499,
            "thb": 21.589661918247725,
            "try": 21.49384252228123,
            "twd": 21.59538190424858,
            "uah": 22.41345806663542,
            "usd": 21.438134311656963,
            "vef": 21.438134311656977,
            "vnd": 21.24593209675648,
            "xag": 18.58740252868557,
            "xau": 21.56176692485284,
            "xdr": 21.203934893227828,
            "xlm": 22.33702031771629,
            "xrp": 21.246046703561646,
            "yfi": 19.795753070272788,
            "zar": 21.74132101257207,
            "bits": 21.164325989321497,
            "link": 20.473544460237633,
            "sats": 21.164325989321505
          },
          "market_cap": "$1,793,527,774",
          "market_cap_btc": "20403.18678810404",
          "total_volume": "$298,097,159",
          "total_volume_btc": "3391.082801585969",
          "sparkline": "https://www.coingecko.com/coins/67164/sparkline.svg",
          "content": {
            "title": "What is pump.fun?",
            "description": "Pump.fun is a Solana-based memecoin generator/launchpad that simplifies the process of creating tokens, allowing users to launch their own memecoins without needing technical expertise."
          }
        }
      }
    },
    {
      "item": {
        "id": "bitcoin",
        "coin_id": 1,
        "name": "Bitcoin",
        "symbol": "BTC",
        "market_cap_rank": 1,
        "thumb": "https://coin-images.coingecko.com/coins/images/1/standard/bitcoin.png?1696501400",
        "small": "https://coin-images.coingecko.com/coins/images/1/small/bitcoin.png?1696501400",
        "large": "https://coin-images.coingecko.com/coins/images/1/large/bitcoin.png?1696501400",
        "slug": "bitcoin",
        "price_btc": 1,
        "score": 5,
        "data": {
          "price": 87906.0952441259,
          "price_btc": "1.0",
          "price_change_percentage_24h": {
            "aed": 0.23458561514928042,
            "ars": 0.46887475329863415,
            "aud": 0.37796357172069434,
            "bch": -1.7523880435538948,
            "bdt": 1.0829401043367173,
            "bhd": 0.2545279281929511,
            "bmd": 0.23458561514926074,
            "bnb": -1.094023045104247,
            "brl": -0.5395427032521608,
            "btc": 0,
            "cad": 0.5597781984667664,
            "chf": 0.45178382957697166,
            "clp": -0.3204633578388303,
            "cny": 0.23890868017191363,
            "czk": 0.084049187423015,
            "dkk": 0.166334635524916,
            "dot": -0.15009702864477473,
            "eos": -0.1285367332256321,
            "eth": -0.5553268376484285,
            "eur": 0.174078803513475,
            "gbp": 0.19964424852769203,
            "gel": 0.1694568493390054,
            "hkd": 0.2867527698946125,
            "huf": 0.18393086439474948,
            "idr": 0.2860936120711004,
            "ils": -0.5584071994101862,
            "inr": 0.38382785516045254,
            "jpy": 0.8983764141570177,
            "krw": 1.0664219792040828,
            "kwd": 0.23719944739796273,
            "lkr": 0.9893960800781594,
            "ltc": -1.2621908401509288,
            "mmk": 0.23458561514925494,
            "mxn": 0.055869255843612194,
            "myr": -0.08125313458338906,
            "ngn": 0.20547098060217567,
            "nok": 0.4488281424347028,
            "nzd": 0.44528902019725813,
            "php": 0.42839073407378087,
            "pkr": 1.1329681527978646,
            "pln": 0.05775410772928202,
            "rub": 0.5439268879144489,
            "sar": 0.2374189845480109,
            "sek": 0.3445785652058766,
            "sgd": 0.24620239852826462,
            "sol": -0.92060476375461,
            "thb": 0.44132146688528817,
            "try": 0.31086369775628153,
            "twd": 0.2823800946594991,
            "uah": 1.0396142247784488,
            "usd": 0.23458561514926074,
            "vef": 0.23458561514927137,
            "vnd": 0.07594261989851783,
            "xag": -1.9851853169262943,
            "xau": 0.4644814537160663,
            "xdr": 0.04127828388453924,
            "xlm": 0.9660141768322509,
            "xrp": 0.062435035315906134,
            "yfi": -1.1300361702381916,
            "zar": 0.4744285596287537,
            "bits": 0.0040281011698883856,
            "link": -0.5741583159151024,
            "sats": 0.0040281011698814
          },
          "market_cap": "$1,756,492,657,806",
          "market_cap_btc": "19981015.0",
          "total_volume": "$39,472,519,175",
          "total_volume_btc": "449030.045372093",
          "sparkline": "https://www.coingecko.com/coins/1/sparkline.svg",
          "content": {
            "title": "About Bitcoin (BTC)",
            "description": "Bitcoin is the world's first decentralized cryptocurrency that enables peer-to-peer electronic cash transactions without intermediaries like banks or governments."
          }
        }
      }
    },
    {
      "item": {
        "id": "aster-2",
        "coin_id": 69040,
        "name": "Aster",
        "symbol": "ASTER",
        "market_cap_rank": 69,
        "thumb": "https://coin-images.coingecko.com/coins/images/69040/standard/_ASTER.png?1757326782",
        "small": "https://coin-images.coingecko.com/coins/images/69040/small/_ASTER.png?1757326782",
        "large": "https://coin-images.coingecko.com/coins/images/69040/large/_ASTER.png?1757326782",
        "slug": "aster-2",
        "price_btc": 0.000007391474372790466,
        "score": 6,
        "data": {
          "price": 0.649756329040568,
          "price_btc": "0.000007391474372790466",
          "price_change_percentage_24h": {
            "aed": 5.8929812811999005,
            "ars": 6.132816174434839,
            "aud": 6.033367676252991,
            "bch": 3.7737893182003703,
            "bdt": 6.789226678854078,
            "bhd": 5.914049368316544,
            "bmd": 5.892981281199894,
            "bnb": 4.46382427955217,
            "brl": 5.062429570052357,
            "btc": 5.575663335009323,
            "cad": 6.219600009564847,
            "chf": 6.02267237332618,
            "clp": 5.306598944743227,
            "cny": 5.892981281199878,
            "czk": 5.689872845161909,
            "dkk": 5.78293122502285,
            "dot": 5.518506192851814,
            "eos": 5.443257728667296,
            "eth": 5.064545501561686,
            "eur": 5.791670389433681,
            "gbp": 5.831327832990107,
            "gel": 5.824175896945697,
            "hkd": 5.9493706540646505,
            "huf": 5.836146408270773,
            "idr": 5.9267755008436955,
            "ils": 5.041566015350693,
            "inr": 6.054714739622855,
            "jpy": 6.521963612191098,
            "krw": 6.7506313149216925,
            "kwd": 5.895742668276881,
            "lkr": 6.69040195135122,
            "ltc": 4.363105872305714,
            "mmk": 5.892981281199862,
            "mxn": 5.6887711971612145,
            "myr": 5.532710301538553,
            "ngn": 5.862223081002002,
            "nok": 6.110738828658095,
            "nzd": 6.103346550831908,
            "php": 6.101329628932009,
            "pkr": 6.842078887168375,
            "pln": 5.705125396701003,
            "rub": 6.410377579847536,
            "sar": 5.895212133791719,
            "sek": 6.0036171530719225,
            "sgd": 5.885135007106429,
            "sol": 4.641792294219101,
            "thb": 6.0251120167324395,
            "try": 5.9415583491718635,
            "twd": 6.030099794039432,
            "uah": 6.7434549871281435,
            "usd": 5.892981281199894,
            "vef": 5.892981281199903,
            "vnd": 5.725382646223921,
            "xag": 3.4071683276083267,
            "xau": 6.000787828699204,
            "xdr": 5.688761455423116,
            "xlm": 6.671494743899865,
            "xrp": 5.694182285767528,
            "yfi": 4.4793532705301535,
            "zar": 6.157357408408122,
            "bits": 5.575663335009322,
            "link": 5.069509166722119,
            "sats": 5.575663335009312
          },
          "market_cap": "$1,594,780,348",
          "market_cap_btc": "18141.87013824662",
          "total_volume": "$133,218,241",
          "total_volume_btc": "1515.459209703003",
          "sparkline": "https://www.coingecko.com/coins/69040/sparkline.svg",
          "content": {
            "title": "About Aster",
            "description": "Aster is a next-generation decentralized perpetual exchange that combines non-custodial trading with advanced features like hidden orders and multi-chain support."
          }
        }
      }
    },
    {
      "item": {
        "id": "lighter",
        "coin_id": 71121,
        "name": "Lighter",
        "symbol": "LIT",
        "market_cap_rank": 157,
        "thumb": "https://coin-images.coingecko.com/coins/images/71121/standard/lighter.png?1765888098",
        "small": "https://coin-images.coingecko.com/coins/images/71121/small/lighter.png?1765888098",
        "large": "https://coin-images.coingecko.com/coins/images/71121/large/lighter.png?1765888098",
        "slug": "lighter",
        "price_btc": 0.000020744717119303653,
        "score": 7,
        "data": {
          "price": 1.823588984092643,
          "price_btc": "0.00002074471711930365",
          "price_change_percentage_24h": {
            "aed": 11.903755211571847,
            "ars": 12.165319961935126,
            "aud": 12.063825028356463,
            "bch": 9.694667326539678,
            "bdt": 12.850873938187544,
            "bhd": 11.926019180674874,
            "bmd": 11.903755211571816,
            "bnb": 10.406133469089697,
            "brl": 11.039503962234136,
            "btc": 11.614495463116526,
            "cad": 12.266806258442013,
            "chf": 12.146239336891853,
            "clp": 11.284088217165591,
            "cny": 11.90858156174917,
            "czk": 11.735693544480407,
            "dkk": 11.827558548813562,
            "dot": 11.47755989657296,
            "eos": 11.46653985184614,
            "eth": 10.993005187327753,
            "eur": 11.836204281956363,
            "gbp": 11.864746020151715,
            "gel": 11.83104424637222,
            "hkd": 11.961995593161495,
            "huf": 11.847203305920186,
            "idr": 11.961259697110505,
            "ils": 11.018443287943857,
            "inr": 12.070372023433164,
            "jpy": 12.64482360256672,
            "krw": 12.83243279614009,
            "kwd": 11.906673342497639,
            "lkr": 12.74643965008333,
            "ltc": 10.236279102850993,
            "mmk": 11.903755211571818,
            "mxn": 11.70423294486807,
            "myr": 11.551146958447378,
            "ngn": 11.871251092185956,
            "nok": 12.142939552806187,
            "nzd": 12.138988410931415,
            "php": 12.120122850084849,
            "pkr": 12.906726181745451,
            "pln": 11.706337228561537,
            "rub": 12.249109560591274,
            "sar": 11.906918437854234,
            "sek": 12.02655338629961,
            "sgd": 11.916724404546555,
            "sol": 10.600669602847097,
            "thb": 12.134558960638556,
            "try": 11.988913481361427,
            "twd": 11.957113857220476,
            "uah": 12.802504120617463,
            "usd": 11.903755211571816,
            "vef": 11.903755211571825,
            "vnd": 11.726643221756916,
            "xag": 9.425561667055359,
            "xau": 12.160415200589139,
            "xdr": 11.687943312458437,
            "xlm": 12.72708371049287,
            "xrp": 11.705124867553339,
            "yfi": 10.395896766534527,
            "zar": 12.171520334593358,
            "bits": 11.614495463116524,
            "link": 10.996179727107194,
            "sats": 11.614495463116526
          },
          "market_cap": "$456,451,655",
          "market_cap_btc": "5192.49353257751",
          "total_volume": "$86,225,378",
          "total_volume_btc": "980.8795149249482",
          "sparkline": "https://www.coingecko.com/coins/71121/sparkline.svg",
          "content": null
        }
      }
    },
    {
      "item": {
        "id": "axie-infinity",
        "coin_id": 13029,
        "name": "Axie Infinity",
        "symbol": "AXS",
        "market_cap_rank": 162,
        "thumb": "https://coin-images.coingecko.com/coins/images/13029/standard/axie_infinity_logo.png?1696512817",
        "small": "https://coin-images.coingecko.com/coins/images/13029/small/axie_infinity_logo.png?1696512817",
        "large": "https://coin-images.coingecko.com/coins/images/13029/large/axie_infinity_logo.png?1696512817",
        "slug": "axie-infinity",
        "price_btc": 0.000029112450602129335,
        "score": 8,
        "data": {
          "price": 2.5591645291023544,
          "price_btc": "0.00002911245060212933",
          "price_change_percentage_24h": {
            "aed": 9.101851867157317,
            "ars": 9.356867425784971,
            "aud": 9.257913774161516,
            "bch": 6.944872155451312,
            "bdt": 10.025256151637924,
            "bhd": 9.123558379637295,
            "bmd": 9.101851867157313,
            "bnb": 7.6648836452277695,
            "brl": 8.259240181758805,
            "btc": 8.85705597440313,
            "cad": 9.45581265659608,
            "chf": 9.338264551171257,
            "clp": 8.497700411266898,
            "cny": 9.106557372715272,
            "czk": 8.937998213873819,
            "dkk": 9.02756305533586,
            "dot": 8.692854154257601,
            "eos": 8.712755610987431,
            "eth": 8.232828107724607,
            "eur": 9.035992312199035,
            "gbp": 9.063819407784269,
            "gel": 9.030961476219783,
            "hkd": 9.158633996343859,
            "huf": 9.046715936986418,
            "idr": 9.157916526033816,
            "ils": 8.238706835381867,
            "inr": 9.264296842233477,
            "jpy": 9.824365009499106,
            "krw": 10.007276748318395,
            "kwd": 9.10469693243147,
            "lkr": 9.923436742547969,
            "ltc": 7.487756962195504,
            "mmk": 9.101851867157293,
            "mxn": 8.907325340813742,
            "myr": 8.75807239946396,
            "ngn": 9.070161602504347,
            "nok": 9.335047388763881,
            "nzd": 9.331195177596205,
            "php": 9.312801982292067,
            "pkr": 10.079709938211817,
            "pln": 8.909376936377926,
            "rub": 9.4385590576994,
            "sar": 9.104935890965377,
            "sek": 9.221575358503754,
            "sgd": 9.114496330858229,
            "sol": 7.853853118435082,
            "thb": 9.326876634140822,
            "try": 9.184877900718769,
            "twd": 9.153874491799211,
            "uah": 9.97809744225066,
            "usd": 9.101851867157313,
            "vef": 9.101851867157315,
            "vnd": 8.929174497750482,
            "xag": 6.685708597605792,
            "xau": 9.352085472357183,
            "xdr": 8.891443576535407,
            "xlm": 9.909202980760972,
            "xrp": 8.932302263791838,
            "yfi": 7.627344229609447,
            "zar": 9.362912550347534,
            "bits": 8.857055974403142,
            "link": 8.233903846693048,
            "sats": 8.857055974403128
          },
          "market_cap": "$431,832,834",
          "market_cap_btc": "4912.428218385862",
          "total_volume": "$714,026,851",
          "total_volume_btc": "8122.600634432476",
          "sparkline": "https://www.coingecko.com/coins/13029/sparkline.svg",
          "content": {
            "title": "What is Axie Infinity?",
            "description": "Axie Infinity is a digital game that fuses NFT collectibles and blockchain. The game allows users to discover, collect, combine, and battle fantasy creatures called Axies. Players can earn Smooth Love Potion (SLP) tokens by winning challenges against their opponents in Ranked PvP mode. With its ever-expanding world of characters and unique storytelling and art direction, Axie Infinity has become a hit for gamers around the world."
          }
        }
      }
    },
    {
      "item": {
        "id": "pax-gold",
        "coin_id": 9519,
        "name": "PAX Gold",
        "symbol": "PAXG",
        "market_cap_rank": 57,
        "thumb": "https://coin-images.coingecko.com/coins/images/9519/standard/paxgold.png?1696509604",
        "small": "https://coin-images.coingecko.com/coins/images/9519/small/paxgold.png?1696509604",
        "large": "https://coin-images.coingecko.com/coins/images/9519/large/paxgold.png?1696509604",
        "slug": "pax-gold",
        "price_btc": 0.05797452522838115,
        "score": 9,
        "data": {
          "price": 5096.319460827899,
          "price_btc": "0.05797452522838115",
          "price_change_percentage_24h": {
            "aed": -0.37928793385928905,
            "ars": -0.14643366875145758,
            "aud": -0.23678807674333696,
            "bch": -2.34882237452132,
            "bdt": 0.46387091973093636,
            "bhd": -0.35946775489148014,
            "bmd": -0.3792879338593109,
            "bnb": -1.6913811296681094,
            "brl": -1.1486752050933213,
            "btc": -0.6028106397500516,
            "cad": -0.05608694978875989,
            "chf": -0.1634199213565244,
            "clp": -0.9309375823444684,
            "cny": -0.3749913448803431,
            "czk": -0.5289024210140704,
            "dkk": -0.44712091932696324,
            "dot": -0.7527430374638027,
            "eos": -0.7345710517765759,
            "eth": -1.1727920241701792,
            "eur": -0.43942417947769546,
            "gbp": -0.4140153066722152,
            "gel": -0.444017827101109,
            "hkd": -0.3274402699985263,
            "huf": -0.4296324562487291,
            "idr": -0.32809539089658013,
            "ils": -1.1674241681234128,
            "inr": -0.23095970833698817,
            "jpy": 0.28043756562052125,
            "krw": 0.4474539576852564,
            "kwd": -0.37669010968276084,
            "lkr": 0.37089979355749697,
            "ltc": -1.8531151973086308,
            "mmk": -0.3792879338593289,
            "mxn": -0.5569097683052965,
            "myr": -0.6931923706696964,
            "ngn": -0.4082242596527247,
            "nok": -0.16635750678125483,
            "nzd": -0.16987495412962167,
            "php": -0.18666974892009466,
            "pkr": 0.5135925779828404,
            "pln": -0.5550364599473236,
            "rub": -0.07184118107242296,
            "sar": -0.3764719170590988,
            "sek": -0.2699686211724731,
            "sgd": -0.36774229594371577,
            "sol": -1.5188334308206553,
            "thb": -0.17381820868259049,
            "try": -0.3034770063464592,
            "twd": -0.3317861653587581,
            "uah": 0.42081038382912034,
            "usd": -0.3792879338593109,
            "vef": -0.3792879338593047,
            "vnd": -0.5369593409309575,
            "xag": -2.5854641705340984,
            "xau": -0.1508000621480083,
            "xdr": -0.5714113797738373,
            "xlm": 0.35790297031087365,
            "xrp": -0.5341033831732815,
            "yfi": -1.7256583050821288,
            "zar": -0.1409138759785031,
            "bits": -0.602810639750054,
            "link": -1.1718097687803903,
            "sats": -0.602810639750046
          },
          "market_cap": "$2,071,668,099",
          "market_cap_btc": "23566.84020018186",
          "total_volume": "$3,651,452,375",
          "total_volume_btc": "41538.0588796717",
          "sparkline": "https://www.coingecko.com/coins/9519/sparkline.svg",
          "content": {
            "title": "What is PAX Gold about?",
            "description": "PAX Gold (PAXG) is an asset-backed token where one token represents one fine troy ounce of a London Good Delivery gold bar, stored in professional vault facilities. Anyone who owns PAXG has ownership rights to that gold under the custody of Paxos Trust Company. Since PAXG represents physical gold, its value is tied directly to the real-time market value of that physical gold."
          }
        }
      }
    },
    {
      "item": {
        "id": "memecoin-2",
        "coin_id": 32528,
        "name": "Memecoin",
        "symbol": "MEME",
        "market_cap_rank": 567,
        "thumb": "https://coin-images.coingecko.com/coins/images/32528/standard/memecoin_%282%29.png?1698912168",
        "small": "https://coin-images.coingecko.com/coins/images/32528/small/memecoin_%282%29.png?1698912168",
        "large": "https://coin-images.coingecko.com/coins/images/32528/large/memecoin_%282%29.png?1698912168",
        "slug": "meme",
        "price_btc": 1.1808766318009524e-8,
        "score": 10,
        "data": {
          "price": 0.0010380636211813168,
          "price_btc": "0.00000001180876631800952",
          "price_change_percentage_24h": {
            "aed": 1.8276233215460247,
            "ars": 2.0656360390266313,
            "aud": 1.9732799974804796,
            "bch": -0.18554248487172834,
            "bdt": 2.6894607885037773,
            "bhd": 1.8478825796484977,
            "bmd": 1.827623321546017,
            "bnb": 0.4864631457697567,
            "brl": 1.0411917088950766,
            "btc": 1.5991488865897172,
            "cad": 2.157984221207488,
            "chf": 2.048273487645112,
            "clp": 1.2637529029716457,
            "cny": 1.8320150934480786,
            "czk": 1.6746944042007106,
            "dkk": 1.7582876226765802,
            "dot": 1.4458950159693607,
            "eos": 1.464469568140146,
            "eth": 1.0165406266277401,
            "eur": 1.7661548694561011,
            "gbp": 1.7921266284949697,
            "gel": 1.7614594581287866,
            "hkd": 1.8806195737933566,
            "huf": 1.7761635100685673,
            "idr": 1.8799499399124735,
            "ils": 1.0220273975234624,
            "inr": 1.9792374825290366,
            "jpy": 2.501963810219195,
            "krw": 2.6726801392532513,
            "kwd": 1.830278695676728,
            "lkr": 2.594430060260421,
            "ltc": 0.3211461612151062,
            "mmk": 1.8276233215459987,
            "mxn": 1.6460666063155303,
            "myr": 1.5067649168272519,
            "ngn": 1.7980459653708671,
            "nok": 2.0452708254888146,
            "nzd": 2.0416754556484014,
            "php": 2.0245086034726056,
            "pkr": 2.7402839374493366,
            "pln": 1.6479814143297227,
            "rub": 2.1418809842841515,
            "sar": 1.8305017219514021,
            "sek": 1.9393643999138697,
            "sgd": 1.8394247315569636,
            "sol": 0.6628333173819888,
            "thb": 2.0376448456381624,
            "try": 1.9051136989015678,
            "twd": 1.8761774032190333,
            "uah": 2.645446326662543,
            "usd": 1.827623321546017,
            "vef": 1.8276233215460125,
            "vnd": 1.6664589982353015,
            "xag": -0.4274266389472988,
            "xau": 2.0611729163201677,
            "xdr": 1.6312437386653587,
            "xlm": 2.5811453166113654,
            "xrp": 1.6693782244156858,
            "yfi": 0.45142662340210493,
            "zar": 2.0712781125236073,
            "bits": 1.5991488865897252,
            "link": 1.0175446420554937,
            "sats": 1.5991488865897125
          },
          "market_cap": "$64,272,066",
          "market_cap_btc": "731.1634573676913",
          "total_volume": "$11,403,654",
          "total_volume_btc": "129.7252681438339",
          "sparkline": "https://www.coingecko.com/coins/32528/sparkline.svg",
          "content": {
            "title": "What is Memecoin?",
            "description": "MEMECOIN (MEME) IS LITERALLY A MEME COIN. NO UTILITY. NO ROADMAP. NO PROMISES. NO EXPECTATIONS OF FINANCIAL RETURN. JUST 100% MEMES 😉"
          }
        }
      }
    },
    {
      "item": {
        "id": "monad",
        "coin_id": 38927,
        "name": "Monad",
        "symbol": "MON",
        "market_cap_rank": 271,
        "thumb": "https://coin-images.coingecko.com/coins/images/38927/standard/mon.png?1766029057",
        "small": "https://coin-images.coingecko.com/coins/images/38927/small/mon.png?1766029057",
        "large": "https://coin-images.coingecko.com/coins/images/38927/large/mon.png?1766029057",
        "slug": "monad",
        "price_btc": 2.1921857329958773e-7,
        "score": 11,
        "data": {
          "price": 0.019270668916745046,
          "price_btc": "0.0000002192185732995877",
          "price_change_percentage_24h": {
            "aed": 7.246896896648202,
            "ars": 7.489798246253988,
            "aud": 7.38907822966752,
            "bch": 5.100609586477188,
            "bdt": 8.15460141675296,
            "bhd": 7.268234353951493,
            "bmd": 7.246896896648184,
            "bnb": 5.799467126040252,
            "brl": 6.405726002646847,
            "btc": 6.925521819218021,
            "cad": 7.577691673239196,
            "chf": 7.378246179833886,
            "clp": 6.653017253076864,
            "cny": 7.246896896648184,
            "czk": 7.041191577607629,
            "dkk": 7.1354397737539985,
            "dot": 6.867633883136626,
            "eos": 6.791423314859242,
            "eth": 6.407868987816164,
            "eur": 7.14429067447652,
            "gbp": 7.18445516610592,
            "gel": 7.1772117875714265,
            "hkd": 7.304007246970963,
            "huf": 7.189335350232022,
            "idr": 7.28112319895822,
            "ils": 6.38459569284805,
            "inr": 7.410698230130018,
            "jpy": 7.883921205393392,
            "krw": 8.115512584176269,
            "kwd": 7.249693589984749,
            "lkr": 8.054513146188603,
            "ltc": 5.697460963716148,
            "mmk": 7.246896896648165,
            "mxn": 7.040075844268941,
            "myr": 6.882019601258895,
            "ngn": 7.21574543140999,
            "nok": 7.467438626214758,
            "nzd": 7.459951832961215,
            "php": 7.457909123308212,
            "pkr": 8.208129377409682,
            "pln": 7.0566391436552784,
            "rub": 7.770908467806234,
            "sar": 7.249156272246184,
            "sek": 7.358947325299546,
            "sgd": 7.238950302468441,
            "sol": 5.979710585889625,
            "thb": 7.3807170157824915,
            "try": 7.296095056311833,
            "twd": 7.385768565300807,
            "uah": 8.10824450202711,
            "usd": 7.246896896648184,
            "vef": 7.246896896648209,
            "vnd": 7.07715539624075,
            "xag": 4.729301090838926,
            "xau": 7.35608182604157,
            "xdr": 7.040065977975941,
            "xlm": 8.035364196904084,
            "xrp": 7.045556117416806,
            "yfi": 5.815194665997829,
            "zar": 7.514653257018705,
            "bits": 6.925521819218024,
            "link": 6.412896116897346,
            "sats": 6.925521819218012
          },
          "market_cap": "$208,724,960",
          "market_cap_btc": "2374.456871304356",
          "total_volume": "$90,279,418",
          "total_volume_btc": "1026.997319422923",
          "sparkline": "https://www.coingecko.com/coins/38927/sparkline.svg",
          "content": {
            "title": "About Monad",
            "description": "Monad is a high-performance Layer 1 blockchain that processes 10,000 transactions per second with near-zero fees while maintaining complete compatibility with the Ethereum Virtual Machine."
          }
        }
      }
    },
    {
      "item": {
        "id": "avalanche-2",
        "coin_id": 12559,
        "name": "Avalanche",
        "symbol": "AVAX",
        "market_cap_rank": 33,
        "thumb": "https://coin-images.coingecko.com/coins/images/12559/standard/Avalanche_Circle_RedWhite_Trans.png?1696512369",
        "small": "https://coin-images.coingecko.com/coins/images/12559/small/Avalanche_Circle_RedWhite_Trans.png?1696512369",
        "large": "https://coin-images.coingecko.com/coins/images/12559/large/Avalanche_Circle_RedWhite_Trans.png?1696512369",
        "slug": "avalanche",
        "price_btc": 0.0001329665564192334,
        "score": 12,
        "data": {
          "price": 11.68858298449462,
          "price_btc": "0.0001329665564192334",
          "price_change_percentage_24h": {
            "aed": 0.5422266954132738,
            "ars": 0.769942771713536,
            "aud": 0.6755193894672353,
            "bch": -1.4375718802411532,
            "bdt": 1.393184963425165,
            "bhd": 0.5622302156210136,
            "bmd": 0.5422266954132472,
            "bnb": -0.8192823179175002,
            "brl": -0.24635737705429286,
            "btc": 0.26062157239668626,
            "cad": 0.8523414342081745,
            "chf": 0.6653645184037096,
            "clp": -0.014525839919130926,
            "cny": 0.5422266954132352,
            "czk": 0.3493812945868169,
            "dkk": 0.4377374501193555,
            "dot": 0.23585046298225412,
            "eos": 0.13488171936447318,
            "eth": -0.20020033052730643,
            "eur": 0.4460350260180398,
            "gbp": 0.4836885856021447,
            "gel": 0.47689803568668504,
            "hkd": 0.5957667227237078,
            "huf": 0.4882636790819611,
            "idr": 0.574313298805786,
            "ils": -0.266166699835736,
            "inr": 0.695787789304978,
            "jpy": 1.1394266547003211,
            "krw": 1.356539816759817,
            "kwd": 0.5448485500643109,
            "lkr": 1.2993538328300032,
            "ltc": -0.8695320103361135,
            "mmk": 0.5422266954132288,
            "mxn": 0.34833531267487283,
            "myr": 0.20016014793642964,
            "ngn": 0.5130227019131804,
            "nok": 0.748980990516554,
            "nzd": 0.741962243249231,
            "php": 0.740047236074675,
            "pkr": 1.4433665585167226,
            "pln": 0.36386313725448977,
            "rub": 1.0334790458580865,
            "sar": 0.5443448233977176,
            "sek": 0.6472721552333027,
            "sgd": 0.5347768922339428,
            "sol": -0.6282725060798166,
            "thb": 0.6676808870377781,
            "try": 0.588349172287016,
            "twd": 0.6724166327938986,
            "uah": 1.3497261076061715,
            "usd": 0.5422266954132472,
            "vef": 0.542226695413244,
            "vnd": 0.38309679135619673,
            "xag": -1.8179785465065126,
            "xau": 0.6445857961466686,
            "xdr": 0.34832606318512177,
            "xlm": 1.3189551699599462,
            "xrp": 0.3887601239982951,
            "yfi": -0.7382176435695412,
            "zar": 0.7932439412497766,
            "bits": 0.26062157239667,
            "link": -0.20154251545863366,
            "sats": 0.2606215723966769
          },
          "market_cap": "$5,041,372,304",
          "market_cap_btc": "57349.45936417117",
          "total_volume": "$256,301,968",
          "total_volume_btc": "2915.630593817178",
          "sparkline": "https://www.coingecko.com/coins/12559/sparkline.svg",
          "content": {
            "title": "What is Avalanche?",
            "description": "Avalanche is a general-purpose blockchain platform founded by Cornell University professor Emin Gün Sirer. Developers can deploy decentralized applications such as decentralized finance, gaming, and NFTs via smart contracts. Validators secure the network through a proof-of-stake consensus protocol, which allows for fast and low-cost transaction processing."
          }
        }
      }
    },
    {
      "item": {
        "id": "seeker",
        "coin_id": 70974,
        "name": "Seeker",
        "symbol": "SKR",
        "market_cap_rank": 348,
        "thumb": "https://coin-images.coingecko.com/coins/images/70974/standard/seeker-logo.jpg?1764922774",
        "small": "https://coin-images.coingecko.com/coins/images/70974/small/seeker-logo.jpg?1764922774",
        "large": "https://coin-images.coingecko.com/coins/images/70974/large/seeker-logo.jpg?1764922774",
        "slug": "seeker",
        "price_btc": 2.7673600824005597e-7,
        "score": 13,
        "data": {
          "price": 0.024326807313209426,
          "price_btc": "0.0000002767360082400559",
          "price_change_percentage_24h": {
            "aed": 4.306992756490258,
            "ars": 4.5432355760683985,
            "aud": 4.44527654560206,
            "bch": 2.246547566684687,
            "bdt": 5.189814838464728,
            "bhd": 4.327745301027914,
            "bmd": 4.306992756490242,
            "bnb": 2.9323383634361924,
            "brl": 3.488880448475187,
            "btc": 4.016230689341197,
            "cad": 4.628719625650949,
            "chf": 4.4347414291910106,
            "clp": 3.729392830779406,
            "cny": 4.306992756490232,
            "czk": 4.106926331782275,
            "dkk": 4.198590950500614,
            "dot": 3.9806517224766726,
            "eos": 3.885780814258403,
            "eth": 3.5483987797217056,
            "eur": 4.207199226024323,
            "gbp": 4.246262709059102,
            "gel": 4.239217889542731,
            "hkd": 4.362537570091501,
            "huf": 4.251009115202512,
            "idr": 4.3402808307416985,
            "ils": 3.468329373013808,
            "inr": 4.466303888088375,
            "jpy": 4.926554644812494,
            "krw": 5.151797527993117,
            "kwd": 4.309712785507752,
            "lkr": 5.092470236291053,
            "ltc": 2.8403589881769458,
            "mmk": 4.306992756490191,
            "mxn": 4.105841183469027,
            "myr": 3.952117655126193,
            "ngn": 4.276695230380168,
            "nok": 4.521488888817246,
            "nzd": 4.514207327184554,
            "php": 4.512220613282864,
            "pkr": 5.24187546460918,
            "pln": 4.1219504416303465,
            "rub": 4.816639867397086,
            "sar": 4.309190196984576,
            "sek": 4.415971604250854,
            "sgd": 4.299263998218148,
            "sol": 3.0995741667360868,
            "thb": 4.437144533381875,
            "try": 4.354842272253973,
            "twd": 4.442057607365978,
            "uah": 5.144728682049576,
            "usd": 4.306992756490242,
            "vef": 4.306992756490243,
            "vnd": 4.141904292713689,
            "xag": 1.8584105123495744,
            "xau": 4.413184655453291,
            "xdr": 4.105831587635586,
            "xlm": 5.112616854333548,
            "xrp": 4.145724517307732,
            "yfi": 2.9796167265584264,
            "zar": 4.567409249179867,
            "bits": 4.016230689341201,
            "link": 3.532843420037827,
            "sats": 4.016230689341208
          },
          "market_cap": "$138,718,756",
          "market_cap_btc": "1578.074129640275",
          "total_volume": "$77,629,400",
          "total_volume_btc": "883.0937032614604",
          "sparkline": "https://www.coingecko.com/coins/70974/sparkline.svg",
          "content": null
        }
      }
    },
    {
      "item": {
        "id": "tether-gold",
        "coin_id": 10481,
        "name": "Tether Gold",
        "symbol": "XAUT",
        "market_cap_rank": 50,
        "thumb": "https://coin-images.coingecko.com/coins/images/10481/standard/Tether_Gold.png?1696510471",
        "small": "https://coin-images.coingecko.com/coins/images/10481/small/Tether_Gold.png?1696510471",
        "large": "https://coin-images.coingecko.com/coins/images/10481/large/Tether_Gold.png?1696510471",
        "slug": "tether-gold",
        "price_btc": 0.057779341855673766,
        "score": 14,
        "data": {
          "price": 5079.161634751012,
          "price_btc": "0.05777934185567376",
          "price_change_percentage_24h": {
            "aed": -0.2834217929405768,
            "ars": -0.057575711371357835,
            "aud": -0.15122369281962922,
            "bch": -2.279007983427149,
            "bdt": 0.5605484419758962,
            "bhd": -0.2635825407897773,
            "bmd": -0.28342179294059144,
            "bnb": -1.6292205814980112,
            "brl": -1.0655300465530084,
            "btc": -0.5822315857614345,
            "cad": 0.02414629681226399,
            "chf": -0.1612951725139967,
            "clp": -0.8356023001382089,
            "cny": -0.2834217929405876,
            "czk": -0.4746835555395176,
            "dkk": -0.38705297699733837,
            "dot": -0.6360549323806614,
            "eos": -0.7069143913649263,
            "eth": -1.0635375306442356,
            "eur": -0.37882354043892064,
            "gbp": -0.34147919028424767,
            "gel": -0.3482139764926967,
            "hkd": -0.23032143405671981,
            "huf": -0.33694166727745517,
            "idr": -0.25159868337011354,
            "ils": -1.0851766960184972,
            "inr": -0.13112173621913514,
            "jpy": 0.3088739856869482,
            "krw": 0.5242042236959704,
            "kwd": -0.2808214688483669,
            "lkr": 0.46748784863340964,
            "ltc": -1.7240644022269043,
            "mmk": -0.283421792940625,
            "mxn": -0.4757209478925103,
            "myr": -0.622679304481766,
            "ngn": -0.31238596448844747,
            "nok": -0.07836535531296598,
            "nzd": -0.0853264649263089,
            "php": -0.08722574614337597,
            "pkr": 0.610317947943353,
            "pln": -0.46032063714773686,
            "rub": 0.2037964141012397,
            "sar": -0.281321058933025,
            "sek": -0.17923896196772776,
            "sgd": -0.29081041865316803,
            "sol": -1.4616328789120865,
            "thb": -0.15899782580060542,
            "try": -0.23767807188477216,
            "twd": -0.15430096978716737,
            "uah": 0.5174464684320502,
            "usd": -0.28342179294059144,
            "vef": -0.28342179294058617,
            "vnd": -0.4412449289952807,
            "xag": -2.6242451298215888,
            "xau": -0.18190326078783262,
            "xdr": -0.4757301214258015,
            "xlm": 0.44968343886340256,
            "xrp": -0.470625470990564,
            "yfi": -1.6145973475064948,
            "zar": -0.03446589004810971,
            "bits": -0.5822315857614321,
            "link": -1.0588633803920036,
            "sats": -0.5822315857614245
          },
          "market_cap": "$2,641,427,026",
          "market_cap_btc": "30048.24931663214",
          "total_volume": "$406,015,476",
          "total_volume_btc": "4618.736053625408",
          "sparkline": "https://www.coingecko.com/coins/10481/sparkline.svg",
          "content": {
            "title": "What is Tether Gold?",
            "description": "Tether Gold is a digital token backed by physical gold. It can be used for easy transportation, divisibility, 24/7 trading, and easy redeemability. What's unique about the project is that it provides ownership of real physical gold with the benefits of a crypto asset, making it a neutral monetary unit with direct gold exposure and no custodian fees."
          }
        }
      }
    }
  ],
  "categories": [
    {
      "id": 36,
      "name": "Stablecoins",
      "market_cap_1h_change": 0.04461678495324971,
      "slug": "stablecoins",
      "coins_count": "390",
      "data": {
        "market_cap": 312651891571.72644,
        "market_cap_btc": 3556060.095524473,
        "total_volume": 92359858379.88937,
        "total_volume_btc": 1050488.46869896,
        "market_cap_change_percentage_24h": {
          "aed": -0.2465142166894676,
          "ars": 1.382782405590368,
          "aud": -0.21740868486417744,
          "bch": -3.094182931555383,
          "bdt": 0.36274039900769034,
          "bhd": 0.5246436702842786,
          "bmd": -0.2465142166894716,
          "bnb": -2.1313901943290263,
          "brl": -0.20789912720838308,
          "btc": -1.773999821141732,
          "cad": -0.08655228181485573,
          "chf": -0.33627097896262714,
          "clp": -0.854470248341268,
          "cny": -0.4968420245946993,
          "czk": -0.36582571731117436,
          "dkk": -0.31257450165972256,
          "dot": -1.8009075042759515,
          "eos": 0.4398021734577465,
          "eth": -3.4883713737161086,
          "eur": -0.31052087252610566,
          "gbp": -0.3349794561336365,
          "gel": -0.32062527596386714,
          "hkd": -0.17260003382979858,
          "huf": -0.21972387317337788,
          "idr": -0.5554632574051696,
          "ils": -0.9300525913502752,
          "inr": -0.17056995682871937,
          "jpy": -0.5823243578141852,
          "krw": -0.1143744464718037,
          "kwd": 0.13639219533148214,
          "lkr": 0.27071855545983625,
          "ltc": -2.997988855909316,
          "mmk": -0.24651421668947815,
          "mxn": -0.41081852515519274,
          "myr": -1.5166247584317523,
          "ngn": -0.5179797485233004,
          "nok": 0.2245824412477023,
          "nzd": -0.2337287695515027,
          "php": -0.09205021921645937,
          "pkr": 0.4128244309233286,
          "pln": -0.36169637670334603,
          "rub": 1.8110041505755428,
          "sar": -0.18598641778634556,
          "sek": 0.15976045098910255,
          "sgd": -0.44482832146050993,
          "sol": -4.037965790445846,
          "thb": 0.5655390492478399,
          "try": -0.2696333340544243,
          "twd": 0.036788790514892325,
          "uah": 0.3201445402123743,
          "usd": -0.2465142166894716,
          "vef": -0.2465142166894457,
          "vnd": -0.6470809755613718,
          "xag": -6.452037026569872,
          "xau": -1.1514901473882857,
          "xdr": -0.6710186763365736,
          "xlm": -1.2420640857262735,
          "xrp": -2.9759529730868057,
          "yfi": -3.5696719465567304,
          "zar": -0.49663606219391515,
          "bits": -1.7739998211417338,
          "link": -3.5278307014888663,
          "sats": -1.773999821141735
        },
        "sparkline": "https://www.coingecko.com/categories/36/sparkline.svg"
      }
    },
    {
      "id": 64,
      "name": "Tokenized Gold",
      "market_cap_1h_change": -0.02827747027666618,
      "slug": "tokenized-gold",
      "coins_count": "21",
      "data": {
        "market_cap": 5284669085.285334,
        "market_cap_btc": 60107.1074854627,
        "total_volume": 3770817595.0774517,
        "total_volume_btc": 42888.76651264471,
        "market_cap_change_percentage_24h": {
          "aed": 1.1257651884547728,
          "ars": 2.7896139019949397,
          "aud": 1.1067562707017533,
          "bch": -1.7800198213219198,
          "bdt": 1.7434011409548262,
          "bhd": 1.907531667981445,
          "bmd": 1.1257651884547704,
          "bnb": -0.7993778604749906,
          "brl": 1.1649114943801213,
          "btc": -0.438607451277843,
          "cad": 1.2510504170210754,
          "chf": 1.0223075983619896,
          "clp": 0.5094456842393963,
          "cny": 0.8719936944204066,
          "czk": 0.9640836821055392,
          "dkk": 1.0287130445203119,
          "dot": -0.4622005955027704,
          "eos": 1.8052914045049717,
          "eth": -2.1703364387845476,
          "eur": 1.027806823661358,
          "gbp": 1.0036486381375924,
          "gel": 1.05063460510523,
          "hkd": 1.1995147996107614,
          "huf": 1.115834849056932,
          "idr": 0.8125660265279512,
          "ils": 0.432823577137056,
          "inr": 1.2027541911926838,
          "jpy": 0.7528011740870936,
          "krw": 1.2597227666803241,
          "kwd": 1.5139391315217041,
          "lkr": 1.6501133799331584,
          "ltc": -1.6878687621013422,
          "mmk": 1.1257651884547675,
          "mxn": 0.9402335900033199,
          "myr": -0.16181789096385282,
          "ngn": 0.8505651850321819,
          "nok": 1.5362714243389513,
          "nzd": 1.0883466849887022,
          "php": 1.2823541017731053,
          "pkr": 1.7941741641872142,
          "pln": 0.9757877056846846,
          "rub": 3.2137784410243992,
          "sar": 1.1871256505096976,
          "sek": 1.4384763670504854,
          "sgd": 0.9269461701725882,
          "sol": -2.7201294485416017,
          "thb": 1.9520008194140508,
          "try": 1.1022371624584986,
          "twd": 1.4129655119198101,
          "uah": 1.70021930344094,
          "usd": 1.1257651884547704,
          "vef": 1.1257651884547801,
          "vnd": 0.719687950332227,
          "xag": -5.065506197017936,
          "xau": 0.2083397696794065,
          "xdr": 0.6954209456382777,
          "xlm": 0.09296177860031354,
          "xrp": -1.6619464605162864,
          "yfi": -2.24829976896074,
          "zar": 0.7075012471707072,
          "bits": -0.4386074512778471,
          "link": -2.2159670271680825,
          "sats": -0.43860745127784156
        },
        "sparkline": "https://www.coingecko.com/categories/64/sparkline.svg"
      }
    },
    {
      "id": 305,
      "name": "Tokenized Commodities",
      "market_cap_1h_change": -0.10422178707761946,
      "slug": "tokenized-commodities",
      "coins_count": "41",
      "data": {
        "market_cap": 5857502931.129486,
        "market_cap_btc": 66631.64551949332,
        "total_volume": 3806947776.012529,
        "total_volume_btc": 43305.68805598141,
        "market_cap_change_percentage_24h": {
          "aed": 1.5488938993614767,
          "ars": 3.207515335266865,
          "aud": 1.578523285643119,
          "bch": -1.378211458709665,
          "bdt": 2.169114153734603,
          "bhd": 2.333931432927641,
          "bmd": 1.5488938993615036,
          "bnb": -0.35614320049660875,
          "brl": 1.5882040005959261,
          "btc": 0.007729906908378101,
          "cad": 1.7117349011065657,
          "chf": 1.457521654499557,
          "clp": 0.9299956015336371,
          "cny": 1.2940605789475337,
          "czk": 1.427434976673558,
          "dkk": 1.481644631661925,
          "dot": -0.009478125460322465,
          "eos": 2.261688243195513,
          "eth": -1.727623692698779,
          "eur": 1.483735222936631,
          "gbp": 1.4588364227374506,
          "gel": 1.473448955899825,
          "hkd": 1.6241384229381477,
          "huf": 1.576166427533095,
          "idr": 1.2343842548153305,
          "ils": 0.8530528935107871,
          "inr": 1.6262050381784152,
          "jpy": 1.2070396962364431,
          "krw": 1.6834119806130163,
          "kwd": 1.938692033254926,
          "lkr": 2.075436059646117,
          "ltc": -1.2237706130317858,
          "mmk": 1.5488938993615033,
          "mxn": 1.3816323680318503,
          "myr": 0.25592333666837064,
          "ngn": 1.2725424087537742,
          "nok": 2.028469566893788,
          "nzd": 1.5619094647292553,
          "php": 1.7061380093540988,
          "pkr": 2.220099620589383,
          "pln": 1.4316386390114253,
          "rub": 3.6434444078745347,
          "sar": 1.6105111048206004,
          "sek": 1.9624808812912165,
          "sgd": 1.3470104481115956,
          "sol": -2.2901496218008908,
          "thb": 2.3755628653205374,
          "try": 1.5253586737209743,
          "twd": 1.8372959215470652,
          "uah": 2.125751635508879,
          "usd": 1.5488938993615036,
          "vef": 1.5488938993615098,
          "vnd": 1.1411175597491157,
          "xag": -4.768318701905249,
          "xau": 0.6276298047148677,
          "xdr": 1.1167490174658408,
          "xlm": 0.5604657702533304,
          "xrp": -1.2047168852912857,
          "yfi": -1.824191215642952,
          "zar": 1.2942702483522763,
          "bits": 0.0077299069083840545,
          "link": -1.7721581595064213,
          "sats": 0.007729906908369397
        },
        "sparkline": "https://www.coingecko.com/categories/305/sparkline.svg"
      }
    },
    {
      "id": 49,
      "name": "Tokenized Assets",
      "market_cap_1h_change": -0.1106703623473339,
      "slug": "tokenized-products",
      "coins_count": "548",
      "data": {
        "market_cap": 10872457750.487026,
        "market_cap_btc": 123681.55177626612,
        "total_volume": 4169416039.385923,
        "total_volume_btc": 47429.9240876797,
        "market_cap_change_percentage_24h": {
          "aed": 1.3150846292532963,
          "ars": 2.9698872045839253,
          "aud": 1.3446457959322882,
          "bch": -1.6368162908620083,
          "bdt": 1.9338768695987065,
          "bhd": 2.09831466846196,
          "bmd": 1.315084629253286,
          "bnb": -0.6360837499198366,
          "brl": 1.3543042217118457,
          "btc": -0.2187840947082007,
          "cad": 1.4775507009100466,
          "chf": 1.2239227626343536,
          "clp": 0.6976113017400186,
          "cny": 1.0608380448475518,
          "czk": 1.193905357292892,
          "dkk": 1.247990198318485,
          "dot": -0.28959323813991655,
          "eos": 2.030069104978952,
          "eth": -2.083828022951988,
          "eur": 1.2500759761520583,
          "gbp": 1.2252345037097556,
          "gel": 1.2398133925302055,
          "hkd": 1.3901559075442267,
          "huf": 1.342294364324338,
          "idr": 1.0012991213038627,
          "ils": 0.6208457489545605,
          "inr": 1.3922177645465446,
          "jpy": 0.9740175216705659,
          "krw": 1.4492929919723139,
          "kwd": 1.7039852800360946,
          "lkr": 1.8404144628108032,
          "ltc": -1.4705078713799746,
          "mmk": 1.315084629253272,
          "mxn": 1.148208205974095,
          "myr": 0.025091041413593123,
          "ngn": 1.0393694187451372,
          "nok": 1.7935561071437183,
          "nzd": 1.3280702271864082,
          "php": 1.4719666956118238,
          "pkr": 1.9847449459598012,
          "pln": 1.198099340990428,
          "rub": 3.4048125808009666,
          "sar": 1.3765599653795202,
          "sek": 1.7277193559032462,
          "sgd": 1.1136660006181769,
          "sol": -2.547480923695743,
          "thb": 2.1398502473753043,
          "try": 1.2916035918339934,
          "twd": 1.602822625828,
          "uah": 1.8906141905573572,
          "usd": 1.315084629253286,
          "vef": 1.3150846292532867,
          "vnd": 0.9082471663206013,
          "xag": -4.987583029073128,
          "xau": 0.39594168115261624,
          "xdr": 0.8839347309122142,
          "xlm": 0.3420541485847666,
          "xrp": -1.4373276315011583,
          "yfi": -2.0998857193914673,
          "zar": 1.0610472315030424,
          "bits": -0.2187840947082018,
          "link": -2.0189606854757947,
          "sats": -0.2187840947082106
        },
        "sparkline": "https://www.coingecko.com/categories/49/sparkline.svg"
      }
    },
    {
      "id": 39,
      "name": "Exchange-based Tokens",
      "market_cap_1h_change": -0.11300842058366649,
      "slug": "exchange-based-tokens",
      "coins_count": "407",
      "data": {
        "market_cap": 173851858122.3872,
        "market_cap_btc": 1977367.3912347779,
        "total_volume": 3176511362.8924522,
        "total_volume_btc": 36129.20825067354,
        "market_cap_change_percentage_24h": {
          "aed": 2.893878887484823,
          "ars": 4.586818839029896,
          "aud": 2.874537612020398,
          "bch": -0.06271175300970165,
          "bdt": 3.5223137752176155,
          "bhd": 3.6893140104014184,
          "bmd": 2.893878887484824,
          "bnb": 0.9350760507545822,
          "brl": 2.9337096393537454,
          "btc": 1.302154279739472,
          "cad": 3.021354641171038,
          "chf": 2.7886124133557075,
          "clp": 2.266783465219764,
          "cny": 2.6356703753059065,
          "czk": 2.7293704924023143,
          "dkk": 2.7951298542868863,
          "dot": 1.2781486257903607,
          "eos": 3.5852861469981763,
          "eth": -0.45985278517028105,
          "eur": 2.7942077887862413,
          "gbp": 2.769627214183996,
          "gel": 2.817434698118189,
          "hkd": 2.9689179593192003,
          "huf": 2.8837749230064595,
          "idr": 2.575203655956012,
          "ils": 2.188821673844434,
          "inr": 2.9722139894108293,
          "jpy": 2.5143938566203126,
          "krw": 3.0301786208348416,
          "kwd": 3.2888397820775723,
          "lkr": 3.427394942550574,
          "ltc": 0.03105050341552795,
          "mmk": 2.8938788874848376,
          "mxn": 2.705103398020924,
          "myr": 1.58378331308418,
          "ngn": 2.613867203328683,
          "nok": 3.3115625395087207,
          "nzd": 2.8558061475000023,
          "php": 3.053205649087802,
          "pkr": 3.5739745294624625,
          "pln": 2.7412791526967992,
          "rub": 5.018399600133947,
          "sar": 2.9563121945593767,
          "sek": 3.212057603633267,
          "sgd": 2.691583656892184,
          "sol": -1.01925854347238,
          "thb": 3.734560674030696,
          "try": 2.869939490311309,
          "twd": 3.186100708936459,
          "uah": 3.478376933295918,
          "usd": 2.893878887484824,
          "vef": 2.89387888748484,
          "vnd": 2.480701671169281,
          "xag": -3.405642573828243,
          "xau": 1.9604129230804412,
          "xdr": 2.4560103747693085,
          "xlm": 1.8430176280411463,
          "xrp": 0.05742603842192718,
          "yfi": -0.5391792499724404,
          "zar": 2.468301891975492,
          "bits": 1.3021542797394736,
          "link": -0.5062811926681148,
          "sats": 1.3021542797394723
        },
        "sparkline": "https://www.coingecko.com/categories/39/sparkline.svg"
      }
    },
    {
      "id": 92,
      "name": "Perpetuals",
      "market_cap_1h_change": -0.17542392670586426,
      "slug": "decentralized-perpetuals",
      "coins_count": "111",
      "data": {
        "market_cap": 12290330628.127045,
        "market_cap_btc": 139801.98767637543,
        "total_volume": 1017010293.0084374,
        "total_volume_btc": 11568.448787254449,
        "market_cap_change_percentage_24h": {
          "aed": 13.701341546218815,
          "ars": 15.55845170407685,
          "aud": 13.734516707858141,
          "bch": 10.376110040767996,
          "bdt": 14.39578411736336,
          "bhd": 14.58032522888762,
          "bmd": 13.701341546218798,
          "bnb": 11.503041594544076,
          "brl": 13.745355922693465,
          "btc": 11.97288095762948,
          "cad": 13.883669877391942,
          "chf": 13.599034702471272,
          "clp": 13.00837913135057,
          "cny": 13.416012092699983,
          "czk": 13.565347524796357,
          "dkk": 13.626044498049867,
          "dot": 11.89455415837066,
          "eos": 14.496507968336203,
          "eth": 9.893934893171712,
          "eur": 13.628385272266371,
          "gbp": 13.600506810209051,
          "gel": 13.61686803838356,
          "hkd": 13.7855906497408,
          "huf": 13.731877802414195,
          "idr": 13.349194249079718,
          "ils": 12.922228620119355,
          "inr": 13.787904578689247,
          "jpy": 13.318577342533278,
          "krw": 13.851957527478856,
          "kwd": 14.137787174073882,
          "lkr": 14.290895481334331,
          "ltc": 10.564733701267816,
          "mmk": 13.701341546218792,
          "mxn": 13.514063676702015,
          "myr": 12.253640031087802,
          "ngn": 13.391918823687405,
          "nok": 14.238308466069128,
          "nzd": 13.715914696023512,
          "php": 13.877403200559632,
          "pkr": 14.452871060983785,
          "pln": 13.570054243194448,
          "rub": 16.04654880165445,
          "sar": 13.770332538183478,
          "sek": 14.16442285499272,
          "sgd": 13.475298520424356,
          "sol": 9.35843025577491,
          "thb": 14.626938732312386,
          "try": 13.674989838916346,
          "twd": 14.024256898301731,
          "uah": 14.347232367504073,
          "usd": 13.701341546218798,
          "vef": 13.701341546218817,
          "vnd": 13.244766244564776,
          "xag": 6.628142420007295,
          "xau": 12.669828947140187,
          "xdr": 13.217481496865984,
          "xlm": 12.600238875959635,
          "xrp": 10.605628246480535,
          "yfi": 9.85922691412564,
          "zar": 13.416246853431321,
          "bits": 11.972880957629483,
          "link": 9.953617970851077,
          "sats": 11.972880957629489
        },
        "sparkline": "https://www.coingecko.com/categories/92/sparkline.svg"
      }
    }
  ]
}